{
  "signals": [
    {
      "token": "CSS",
      "symbol": "CSS",
      "address": "4k7HHPNkYNbX6zdG162MNKytEt16uyP8wvfCU2jLxCSS",
      "label": "WATCH",
      "score": 40,
      "tech_score": 40,
      "narr_bonus": 0,
      "narrative": null,
      "all_narratives": [],
      "price": 5.951e-05,
      "change_1h": 38.66,
      "liquidity": 19426.25,
      "volume_1h": 12624.69,
      "mcap": 59517.0,
      "dex_url": "https://dexscreener.com/solana/9e9vk7wmszcylhfxsxypy37brfk3l5ty53q3bcgve9dj",
      "time": "20:58:19",
      "date": "2026-05-07",
      "traded": false,
      "tx": null
    },
    {
      "token": "Hantavirus HFRS",
      "symbol": "HFRS",
      "address": "8Znyt9AppSvCvtRrXGz2SV7huo1cUj6cT7vCqAAppump",
      "label": "STRONG BUY",
      "score": 71,
      "tech_score": 71,
      "narr_bonus": 0,
      "narrative": null,
      "all_narratives": [],
      "price": 0.000144,
      "change_1h": 206.0,
      "liquidity": 31070.95,
      "volume_1h": 247852.2,
      "mcap": 144061.0,
      "dex_url": "https://dexscreener.com/solana/bxzbjjsr7ewzeez2rmjnyljp6lhafmneurrbmeyckb19",
      "time": "20:58:20",
      "date": "2026-05-07",
      "traded": false,
      "tx": null
    },
    {
      "token": "Topless",
      "symbol": "Topless",
      "address": "A1FDAwwK52UgoiLah81ffzxWnyhaygKGGD4w81rkpump",
      "label": "WATCH",
      "score": 48,
      "tech_score": 48,
      "narr_bonus": 0,
      "narrative": null,
      "all_narratives": [],
      "price": 7.019e-05,
      "change_1h": 95.46,
      "liquidity": 21045.07,
      "volume_1h": 116033.36,
      "mcap": 70199.0,
      "dex_url": "https://dexscreener.com/solana/3ugrefoc6qpwx4f1c96gqaiwybtni5swjyzjwtezcefy",
      "time": "20:58:20",
      "date": "2026-05-07",
      "traded": false,
      "tx": null
    },
    {
      "token": "The Original Doge",
      "symbol": "OGDOGE",
      "address": "utLyQQCPvjuCc6zeaXdsFeEC3JNdxKS3vxaZWoGdoge",
      "label": "BUY",
      "score": 56,
      "tech_score": 34,
      "narr_bonus": 22,
      "narrative": "\ud83c\udfdb\ufe0f PolitiFi",
      "all_narratives": [
        "\ud83c\udfdb\ufe0f PolitiFi",
        "\ud83d\udc3e Animal"
      ],
      "price": 0.0001208,
      "change_1h": 13.45,
      "liquidity": 27985.16,
      "volume_1h": 212205.68,
      "mcap": 120846.0,
      "dex_url": "https://dexscreener.com/solana/6wgsajrfy9fxgxkzrfns3rnt2yrgmhrs1xafpmkr8ykd",
      "time": "20:58:21",
      "date": "2026-05-07",
      "traded": false,
      "tx": null
    },
    {
      "token": "Runner",
      "symbol": "Runner",
      "address": "C1QVo85W419fJri4hNtAULNTqYxZvj5pfBhVGVgLpump",
      "label": "WATCH",
      "score": 35,
      "tech_score": 35,
      "narr_bonus": 0,
      "narrative": null,
      "all_narratives": [],
      "price": 4.49e-05,
      "change_1h": 23.2,
      "liquidity": 16735.14,
      "volume_1h": 88245.25,
      "mcap": 44901.0,
      "dex_url": "https://dexscreener.com/solana/czkppnxgv8tuhmmyty9pqicts38xftxcxa5khyuyqiqw",
      "time": "20:58:21",
      "date": "2026-05-07",
      "traded": false,
      "tx": null
    },
    {
      "token": "Plandemic",
      "symbol": "PLANDEMIC",
      "address": "HPjpSWqAAK4iq7yEk2e7NKha4aoNgiEBnBnWRGdHpump",
      "label": "BUY",
      "score": 56,
      "tech_score": 56,
      "narr_bonus": 0,
      "narrative": null,
      "all_narratives": [],
      "price": 0.0001249,
      "change_1h": 110.0,
      "liquidity": 28380.21,
      "volume_1h": 128429.74,
      "mcap": 124904.0,
      "dex_url": "https://dexscreener.com/solana/5ajhje3a79idtsc9v4kjls99camug9xmxtwgkbutcpkq",
      "time": "20:58:21",
      "date": "2026-05-07",
      "traded": false,
      "tx": null
    },
    {
      "token": "I AM OUT",
      "symbol": "IMOUT",
      "address": "DACYVx34V5aQaehN3MZGYxPfoyQYHZSnFAFw3T2Vbonk",
      "label": "WATCH",
      "score": 21,
      "tech_score": 21,
      "narr_bonus": 0,
      "narrative": null,
      "all_narratives": [],
      "price": 0.0007608,
      "change_1h": 1.07,
      "liquidity": 137643.25,
      "volume_1h": 31789.07,
      "mcap": 760761.0,
      "dex_url": "https://dexscreener.com/solana/2i1ctvedhpvvyrdyzt26vsavd17h6ctqs9eq9xoyxfmr",
      "time": "20:58:22",
      "date": "2026-05-07",
      "traded": false,
      "tx": null
    },
    {
      "token": "Russian Oil Asset Fund",
      "symbol": "ROAF",
      "address": "RoAFTaaY51FvFTiEaiVYbg8bjFnGkBMzEor85JwVibe",
      "label": "WATCH",
      "score": 45,
      "tech_score": 33,
      "narr_bonus": 12,
      "narrative": "\ud83d\ude02 Meme Culture",
      "all_narratives": [
        "\ud83d\ude02 Meme Culture"
      ],
      "price": 0.01064,
      "change_1h": 7.85,
      "liquidity": 277054.42,
      "volume_1h": 78154.9,
      "mcap": 10643061.0,
      "dex_url": "https://dexscreener.com/solana/2uywng1pmhtcwxuhgfu51pnsfxsvp7z8mlnva6m4rycs",
      "time": "20:58:22",
      "date": "2026-05-07",
      "traded": false,
      "tx": null
    },
    {
      "token": "Pandu Pandas",
      "symbol": "PANDU",
      "address": "2xm2WZ9krE2YAArRC6S6ZzJAYgN813K6hh2dawKjpump",
      "label": "BUY",
      "score": 50,
      "tech_score": 30,
      "narr_bonus": 20,
      "narrative": "\ud83d\udc3e Animal",
      "all_narratives": [
        "\ud83d\udc3e Animal"
      ],
      "price": 0.001468,
      "change_1h": 7.33,
      "liquidity": 101379.2,
      "volume_1h": 9514.82,
      "mcap": 1416648.0,
      "dex_url": "https://dexscreener.com/solana/bfn7n6xpsx4zslwbmffvaadkgvqbydcwwaj8ugdiphr6",
      "time": "20:58:22",
      "date": "2026-05-07",
      "traded": false,
      "tx": null
    },
    {
      "token": "Werld Helth Orgenization",
      "symbol": "WHO",
      "address": "FGijtUZ5QqbrTfRi72WEHpprXn6DKPhYDQFwFrFwSYZa",
      "label": "WATCH",
      "score": 35,
      "tech_score": 35,
      "narr_bonus": 0,
      "narrative": null,
      "all_narratives": [],
      "price": 0.0001367,
      "change_1h": 45.21,
      "liquidity": 30149.34,
      "volume_1h": 85557.16,
      "mcap": 136759.0,
      "dex_url": "https://dexscreener.com/solana/92ka9e9x6j5eef4ylzpaugawekyyde4rhrkrk4r4tyiq",
      "time": "20:58:22",
      "date": "2026-05-07",
      "traded": false,
      "tx": null
    },
    {
      "token": "ratwifhat",
      "symbol": "RATWIF",
      "address": "B4eAiVxxWMkBUrTkVNGMjqeHPcbqtpzfK52d3NAWpump",
      "label": "STRONG BUY",
      "score": 81,
      "tech_score": 61,
      "narr_bonus": 20,
      "narrative": "\ud83d\udc3e Animal",
      "all_narratives": [
        "\ud83d\udc3e Animal"
      ],
      "price": 9.247e-05,
      "change_1h": 147.0,
      "liquidity": 24695.92,
      "volume_1h": 353534.69,
      "mcap": 92472.0,
      "dex_url": "https://dexscreener.com/solana/9stnmjdmuffkqtmppsxzewsmj4z9z3n5ltuackjtlage",
      "time": "19:52:46",
      "date": "2026-05-07",
      "traded": false,
      "tx": null
    },
    {
      "token": "Hantachan",
      "symbol": "HANTACHAN",
      "address": "xgN6e4tCX4RTtTkeaXxRSTEPLfZQ6tVKQ6xFbPypump",
      "label": "BUY",
      "score": 51,
      "tech_score": 51,
      "narr_bonus": 0,
      "narrative": null,
      "all_narratives": [],
      "price": 6.141e-05,
      "change_1h": 102.0,
      "liquidity": 19660.87,
      "volume_1h": 22801.64,
      "mcap": 61416.0,
      "dex_url": "https://dexscreener.com/solana/hjzmzcetrggof6rdyvtnwefbxeqwtyjctkmnb29ygcx4",
      "time": "19:52:47",
      "date": "2026-05-07",
      "traded": false,
      "tx": null
    },
    {
      "token": "Justice for Goldie",
      "symbol": "Goldie",
      "address": "5Pzo2sySeEsnvVsnUB3AujH3oriGbJro4ASBw5etpump",
      "label": "STRONG BUY",
      "score": 83,
      "tech_score": 83,
      "narr_bonus": 0,
      "narrative": null,
      "all_narratives": [],
      "price": 0.0002151,
      "change_1h": 576.0,
      "liquidity": 38444.42,
      "volume_1h": 356344.44,
      "mcap": 215134.0,
      "dex_url": "https://dexscreener.com/solana/5xcmip1a4gv4oklpp2jq3em4tqa3af4rwuncmgdmauad",
      "time": "19:52:48",
      "date": "2026-05-07",
      "traded": false,
      "tx": null
    },
    {
      "token": "Diet Coke ",
      "symbol": "DC",
      "address": "J6V6zdpMeiXrmrN67skLQu41DZW2rZEuR6K4eCVQpump",
      "label": "WATCH",
      "score": 48,
      "tech_score": 48,
      "narr_bonus": 0,
      "narrative": null,
      "all_narratives": [],
      "price": 5.486e-05,
      "change_1h": 50.7,
      "liquidity": 18566.72,
      "volume_1h": 51365.94,
      "mcap": 54866.0,
      "dex_url": "https://dexscreener.com/solana/fkp5xxldlalbuybhskzcsr1che3fxdt23k2bxjxlqpvh",
      "time": "19:52:49",
      "date": "2026-05-07",
      "traded": false,
      "tx": null
    },
    {
      "token": "Franklin The Turtle",
      "symbol": "Franklin",
      "address": "CSrwNk6B1DwWCHRMsaoDVUfD5bBMQCJPY72ZG3Nnpump",
      "label": "WATCH",
      "score": 43,
      "tech_score": 43,
      "narr_bonus": 0,
      "narrative": null,
      "all_narratives": [],
      "price": 0.0001762,
      "change_1h": 99.79,
      "liquidity": 72354.2,
      "volume_1h": 29640.16,
      "mcap": 173851.0,
      "dex_url": "https://dexscreener.com/solana/8wxzwpljk6qjmyyc1vhuennxrvw2nfgvqjgenv4mv8sy",
      "time": "19:52:50",
      "date": "2026-05-07",
      "traded": false,
      "tx": null
    },
    {
      "token": "Winston",
      "symbol": "Winston",
      "address": "7tQh4cnMcwnhxLzrURBsFMnkeWaXVXRTZQtyNy37pump",
      "label": "WATCH",
      "score": 32,
      "tech_score": 32,
      "narr_bonus": 0,
      "narrative": null,
      "all_narratives": [],
      "price": 4.929e-05,
      "change_1h": 46.26,
      "liquidity": 19403.95,
      "volume_1h": 15420.81,
      "mcap": 49292.0,
      "dex_url": "https://dexscreener.com/solana/hkyot24a8yukyxzgsjbubh9xhidx6t36nwk14s2rhpsh",
      "time": "19:52:50",
      "date": "2026-05-07",
      "traded": false,
      "tx": null
    },
    {
      "token": "Killer Bean",
      "symbol": "KB",
      "address": "2fLF5eJpqaSu5d964Wmj7uaZTW3vyG92gggguCY5pump",
      "label": "WATCH",
      "score": 18,
      "tech_score": 18,
      "narr_bonus": 0,
      "narrative": null,
      "all_narratives": [],
      "price": 2.449e-05,
      "change_1h": 6.9,
      "liquidity": 12953.18,
      "volume_1h": 5140.37,
      "mcap": 24489.0,
      "dex_url": "https://dexscreener.com/solana/a5enart4pbzzzcxpjgx6pchywhie4wcuouj5y2ykuyp8",
      "time": "19:52:51",
      "date": "2026-05-07",
      "traded": false,
      "tx": null
    },
    {
      "token": "The Great Distraction",
      "symbol": "Distraction",
      "address": "F9ELnJHtcY1fUCkvyhUco1hDUwfjCTKtYenoDKbVpump",
      "label": "WATCH",
      "score": 27,
      "tech_score": 27,
      "narr_bonus": 0,
      "narrative": null,
      "all_narratives": [],
      "price": 1.173e-05,
      "change_1h": 35.56,
      "liquidity": 8604.61,
      "volume_1h": 12581.54,
      "mcap": 11736.0,
      "dex_url": "https://dexscreener.com/solana/5vmij3s2yzqumildsu8fjfaj2dcxrsu5nhgpsdhckrui",
      "time": "18:08:10",
      "date": "2026-05-07",
      "traded": false,
      "tx": null
    },
    {
      "token": "Werld Helth Orgenization",
      "symbol": "WHO",
      "address": "FGijtUZ5QqbrTfRi72WEHpprXn6DKPhYDQFwFrFwSYZa",
      "label": "WATCH",
      "score": 48,
      "tech_score": 48,
      "narr_bonus": 0,
      "narrative": null,
      "all_narratives": [],
      "price": 7.223e-05,
      "change_1h": 98.13,
      "liquidity": 21453.4,
      "volume_1h": 125507.45,
      "mcap": 72234.0,
      "dex_url": "https://dexscreener.com/solana/92ka9e9x6j5eef4ylzpaugawekyyde4rhrkrk4r4tyiq",
      "time": "18:08:10",
      "date": "2026-05-07",
      "traded": false,
      "tx": null
    },
    {
      "token": "OnlyAgents",
      "symbol": "OnlyAgents",
      "address": "6EBkShQvBv4StXxdHbKCSCus84dHJsnNKzLmoMf8pump",
      "label": "BUY",
      "score": 57,
      "tech_score": 32,
      "narr_bonus": 25,
      "narrative": "\ud83e\udd16 AI Agent",
      "all_narratives": [
        "\ud83e\udd16 AI Agent"
      ],
      "price": 9.757e-05,
      "change_1h": 40.65,
      "liquidity": 24769.78,
      "volume_1h": 4087.64,
      "mcap": 97578.0,
      "dex_url": "https://dexscreener.com/solana/7s7r8jrrzmcwoqutfdw17fu9z8popetmqm4hmrm17mqe",
      "time": "18:08:10",
      "date": "2026-05-07",
      "traded": false,
      "tx": null
    },
    {
      "token": "Arnai",
      "symbol": "ARNAI",
      "address": "AeEGJHMSRvU1KJPVtGnh97ixDvcTJzKx6bynQrZNCMsA",
      "label": "STRONG BUY",
      "score": 78,
      "tech_score": 53,
      "narr_bonus": 25,
      "narrative": "\ud83e\udd16 AI Agent",
      "all_narratives": [
        "\ud83e\udd16 AI Agent"
      ],
      "price": 0.001573,
      "change_1h": 105.0,
      "liquidity": 6561.59,
      "volume_1h": 6874.85,
      "mcap": 1573511.0,
      "dex_url": "https://dexscreener.com/solana/2vz38ftsvmkkygtr9ap1kdmc8ezhbwracxjivxkweb8c",
      "time": "18:08:11",
      "date": "2026-05-07",
      "traded": false,
      "tx": null
    },
    {
      "token": "NewVirusWarIsraelTerrorist9/11",
      "symbol": "PSYOP",
      "address": "5mgrF9VW4HtSnSgy5jUF7kaCxETkxQvQhPZa2fanpump",
      "label": "WATCH",
      "score": 43,
      "tech_score": 43,
      "narr_bonus": 0,
      "narrative": null,
      "all_narratives": [],
      "price": 3.079e-05,
      "change_1h": 80.92,
      "liquidity": 14007.68,
      "volume_1h": 39719.66,
      "mcap": 30795.0,
      "dex_url": "https://dexscreener.com/solana/g6wadup9e1whstmjpewqzseahqsnubjj5h7feszkzdzg",
      "time": "18:08:12",
      "date": "2026-05-07",
      "traded": false,
      "tx": null
    },
    {
      "token": "LUNA DD",
      "symbol": "LUNADD",
      "address": "4j5NN1CyR24ajbrVErDTg3z7pTUHKxP8iU4Zdkj5pump",
      "label": "WATCH",
      "score": 24,
      "tech_score": 24,
      "narr_bonus": 0,
      "narrative": null,
      "all_narratives": [],
      "price": 3.176e-05,
      "change_1h": 36.57,
      "liquidity": 14168.52,
      "volume_1h": 2910.08,
      "mcap": 31765.0,
      "dex_url": "https://dexscreener.com/solana/9zedpms8cf1qdkd1pdyks5xthyr3bczvqsqh9yodfhvv",
      "time": "18:08:12",
      "date": "2026-05-07",
      "traded": false,
      "tx": null
    },
    {
      "token": "Unstable Unicorn",
      "symbol": "UU",
      "address": "2Y5B9gmNZSHoeQdC9aw9hCxAJthUJbzHmHzBajwepump",
      "label": "WATCH",
      "score": 47,
      "tech_score": 47,
      "narr_bonus": 0,
      "narrative": null,
      "all_narratives": [],
      "price": 4.434e-05,
      "change_1h": 45.5,
      "liquidity": 16729.14,
      "volume_1h": 6242.74,
      "mcap": 39051.0,
      "dex_url": "https://dexscreener.com/solana/2xmantcjh6xdseyo6kc6fgkddbrygbljcxqpsd3d6kzx",
      "time": "18:08:13",
      "date": "2026-05-07",
      "traded": false,
      "tx": null
    },
    {
      "token": "Trench Rat",
      "symbol": "RAT",
      "address": "6VzqDhuZMDKkAmABv5vQ11F2JjZB71Z1LxeEzBLkpump",
      "label": "WATCH",
      "score": 29,
      "tech_score": 29,
      "narr_bonus": 0,
      "narrative": null,
      "all_narratives": [],
      "price": 3.899e-05,
      "change_1h": 5.96,
      "liquidity": 15636.03,
      "volume_1h": 26972.41,
      "mcap": 38994.0,
      "dex_url": "https://dexscreener.com/solana/j53jahuw5bhm1zkxsxwofrktx2qgofkkbmrceaeofacu",
      "time": "16:27:37",
      "date": "2026-05-07",
      "traded": false,
      "tx": null
    },
    {
      "token": "Dai Dai",
      "symbol": "DAIDAI",
      "address": "zuMj7WhAstLoDzqZTFTtvVYbB9K8PMx58FrVBuepump",
      "label": "STRONG BUY",
      "score": 81,
      "tech_score": 56,
      "narr_bonus": 25,
      "narrative": "\ud83e\udd16 AI Agent",
      "all_narratives": [
        "\ud83e\udd16 AI Agent"
      ],
      "price": 7.719e-05,
      "change_1h": 113.0,
      "liquidity": 22342.88,
      "volume_1h": 240653.57,
      "mcap": 77195.0,
      "dex_url": "https://dexscreener.com/solana/4zg6uqsrpzkulqqqmarvjtfjdsitpnxcub2pdjyntpzz",
      "time": "16:27:37",
      "date": "2026-05-07",
      "traded": false,
      "tx": null
    },
    {
      "token": "AIRA",
      "symbol": "AIRA",
      "address": "2CkuXcYQFgPFZ5d5AfTwm2PffsHbt6ETYRcaURH8pump",
      "label": "STRONG BUY",
      "score": 73,
      "tech_score": 48,
      "narr_bonus": 25,
      "narrative": "\ud83e\udd16 AI Agent",
      "all_narratives": [
        "\ud83e\udd16 AI Agent"
      ],
      "price": 6.33e-05,
      "change_1h": 120.0,
      "liquidity": 20261.28,
      "volume_1h": 7946.36,
      "mcap": 63308.0,
      "dex_url": "https://dexscreener.com/solana/7p4unn58c9iaqeickgdcfu4fgukonqgay8m7rth4ypjt",
      "time": "16:27:38",
      "date": "2026-05-07",
      "traded": false,
      "tx": null
    },
    {
      "token": "This Time Is Different",
      "symbol": "DIFFERENT",
      "address": "HvDKt1AuC1uEaiueQiAy1qXzmVA4bHgyW3Nv91bVpump",
      "label": "STRONG BUY",
      "score": 80,
      "tech_score": 80,
      "narr_bonus": 0,
      "narrative": null,
      "all_narratives": [],
      "price": 0.0001729,
      "change_1h": 292.0,
      "liquidity": 34024.41,
      "volume_1h": 533366.49,
      "mcap": 172979.0,
      "dex_url": "https://dexscreener.com/solana/2xk9peoxsyiquz9r5z6js4ddt4e4ek3lqzzueopzvjee",
      "time": "16:27:39",
      "date": "2026-05-07",
      "traded": false,
      "tx": null
    },
    {
      "token": "FAAVIATOR ",
      "symbol": "$FAAV",
      "address": "CEV9ZFRE3GYMEK73nu3JHKkun4Kawdmc5rZ3ehWvpump",
      "label": "WATCH",
      "score": 37,
      "tech_score": 37,
      "narr_bonus": 0,
      "narrative": null,
      "all_narratives": [],
      "price": 0.0012,
      "change_1h": 2.7,
      "liquidity": 86915.86,
      "volume_1h": 652.93,
      "mcap": 1200544.0,
      "dex_url": "https://dexscreener.com/solana/f3bp8pe11lb9cnf3fpd7m8sevveiv5nddwm6jspnre3d",
      "time": "16:27:40",
      "date": "2026-05-07",
      "traded": false,
      "tx": null
    },
    {
      "token": "Dead Scientists Theory ",
      "symbol": "DST",
      "address": "p7U8o21831ce4vRK3hwjAQcb3ZQwcu2vMokemmtpump",
      "label": "WATCH",
      "score": 34,
      "tech_score": 34,
      "narr_bonus": 0,
      "narrative": null,
      "all_narratives": [],
      "price": 0.0005452,
      "change_1h": 12.72,
      "liquidity": 59534.2,
      "volume_1h": 27541.71,
      "mcap": 545229.0,
      "dex_url": "https://dexscreener.com/solana/fbgl8fd9nqzazbhwhhobk6deagokvrnbhuvzql6bcezd",
      "time": "16:27:40",
      "date": "2026-05-07",
      "traded": false,
      "tx": null
    },
    {
      "token": "Menace Shrek",
      "symbol": "Shrek",
      "address": "6ixv7h9LQ8Vz4S9F4Ta8BWM7USaDapihZroDWSRBpump",
      "label": "WATCH",
      "score": 32,
      "tech_score": 32,
      "narr_bonus": 0,
      "narrative": null,
      "all_narratives": [],
      "price": 6.4e-05,
      "change_1h": 26.2,
      "liquidity": 22153.8,
      "volume_1h": 3350.35,
      "mcap": 64004.0,
      "dex_url": "https://dexscreener.com/solana/35vpiwxbynp2x8gvzgcngwizugzuaz2zjmndnnfrbb9w",
      "time": "16:27:40",
      "date": "2026-05-07",
      "traded": false,
      "tx": null
    },
    {
      "token": "Disco By Matt Furie",
      "symbol": "DISCO",
      "address": "8h4a46euwqfiZ9A3GYkiocXeu9pkNnwTaQGHgBf7pump",
      "label": "WATCH",
      "score": 38,
      "tech_score": 38,
      "narr_bonus": 0,
      "narrative": null,
      "all_narratives": [],
      "price": 0.0001519,
      "change_1h": 16.36,
      "liquidity": 31847.37,
      "volume_1h": 2084.5,
      "mcap": 90395.0,
      "dex_url": "https://dexscreener.com/solana/ga3vvp3bdgb2fdtxmmjdhvm9nhr5uqwsx5tj2pf5yuxp",
      "time": "16:27:41",
      "date": "2026-05-07",
      "traded": false,
      "tx": null
    },
    {
      "token": "Track Hantavirus",
      "symbol": "TrackHanta",
      "address": "Dagi5mNUCkrTA8p225LFY1TxxMk5po8Mj1aCyeWCpump",
      "label": "WATCH",
      "score": 43,
      "tech_score": 43,
      "narr_bonus": 0,
      "narrative": null,
      "all_narratives": [],
      "price": 0.0001101,
      "change_1h": 85.22,
      "liquidity": 27343.38,
      "volume_1h": 89329.76,
      "mcap": 110151.0,
      "dex_url": "https://dexscreener.com/solana/8nba1kizsxedsh8f5nkhwlffxjt1jkhn2hiqjgz2c8vn",
      "time": "16:27:41",
      "date": "2026-05-07",
      "traded": false,
      "tx": null
    },
    {
      "token": "UFO: Disclosure ",
      "symbol": "UFO",
      "address": "Gps4KFPSP9WckatkZK95SYbmH3m9EfnTYdj3pcCbpump",
      "label": "WATCH",
      "score": 35,
      "tech_score": 35,
      "narr_bonus": 0,
      "narrative": null,
      "all_narratives": [],
      "price": 6.722e-05,
      "change_1h": 25.93,
      "liquidity": 20550.97,
      "volume_1h": 12170.0,
      "mcap": 67220.0,
      "dex_url": "https://dexscreener.com/solana/12vmcaa7hgciuetkkxkdeua2ajk9engj3uz6ylhg1qaw",
      "time": "16:27:41",
      "date": "2026-05-07",
      "traded": false,
      "tx": null
    },
    {
      "token": "Enemy Of My Enemy",
      "symbol": "EOME",
      "address": "6qkLuxj5is3J4R58QRBCok29je1qsJNNCLp5mT3pump",
      "label": "BUY",
      "score": 53,
      "tech_score": 53,
      "narr_bonus": 0,
      "narrative": null,
      "all_narratives": [],
      "price": 0.0001105,
      "change_1h": 99.29,
      "liquidity": 27407.18,
      "volume_1h": 738286.8,
      "mcap": 110519.0,
      "dex_url": "https://dexscreener.com/solana/47wtu8w6rzcu5qgvias3gzephhezc5eq4ozedy8d7p1o",
      "time": "14:41:47",
      "date": "2026-05-07",
      "traded": false,
      "tx": null
    },
    {
      "token": "Andes Virus",
      "symbol": "ANDV",
      "address": "65q6H7gCPaZZSB7ft1CK5fFMxP1LbW1h7oPudPSPpump",
      "label": "STRONG BUY",
      "score": 80,
      "tech_score": 80,
      "narr_bonus": 0,
      "narrative": null,
      "all_narratives": [],
      "price": 0.0001755,
      "change_1h": 298.0,
      "liquidity": 34145.31,
      "volume_1h": 522390.54,
      "mcap": 175510.0,
      "dex_url": "https://dexscreener.com/solana/frddjqfywxwddvqwjbcf2wvyhormja4iyanthzkqlsz3",
      "time": "14:41:47",
      "date": "2026-05-07",
      "traded": false,
      "tx": null
    },
    {
      "token": "Pandamic",
      "symbol": "Pandamic",
      "address": "ETZKRf2VWzQKi5X3Lr8CzpLHREB5jRB1SWUGzXNGpump",
      "label": "STRONG BUY",
      "score": 73,
      "tech_score": 53,
      "narr_bonus": 20,
      "narrative": "\ud83d\udc3e Animal",
      "all_narratives": [
        "\ud83d\udc3e Animal"
      ],
      "price": 6.726e-05,
      "change_1h": 84.88,
      "liquidity": 20784.3,
      "volume_1h": 211566.7,
      "mcap": 67264.0,
      "dex_url": "https://dexscreener.com/solana/ajk6nuy5przmas3zspwj7kukonw85xxcjz4zq1thfqwg",
      "time": "14:41:48",
      "date": "2026-05-07",
      "traded": false,
      "tx": null
    },
    {
      "token": "We Miss BUSD",
      "symbol": "MISSBUSD",
      "address": "FZUsaHuSnecp9Vb5MeSFCfHJKaJZaCVfZnExCQ8XeFd3",
      "label": "STRONG BUY",
      "score": 83,
      "tech_score": 73,
      "narr_bonus": 10,
      "narrative": "\ud83d\udcb0 DeFi",
      "all_narratives": [
        "\ud83d\udcb0 DeFi"
      ],
      "price": 0.000268,
      "change_1h": 6903.0,
      "liquidity": 44077.44,
      "volume_1h": 100730.89,
      "mcap": 268070.0,
      "dex_url": "https://dexscreener.com/solana/dtrc6plb1ohej9ipjdblrlax9rbpvxm31beqzepyi6z4",
      "time": "14:41:50",
      "date": "2026-05-07",
      "traded": false,
      "tx": null
    },
    {
      "token": "Moo Dang",
      "symbol": "MOODANG",
      "address": "8HyG5qPSp1M5Ez8KvL67NktTyCtHvr6Xn87b2UHNpump",
      "label": "WATCH",
      "score": 32,
      "tech_score": 32,
      "narr_bonus": 0,
      "narrative": null,
      "all_narratives": [],
      "price": 0.0001367,
      "change_1h": 34.71,
      "liquidity": 33315.45,
      "volume_1h": 4803.61,
      "mcap": 136789.0,
      "dex_url": "https://dexscreener.com/solana/bdhlfcbnsmp58zhynfougeajchv8nhpg9gtwgbe5z6pt",
      "time": "14:41:50",
      "date": "2026-05-07",
      "traded": false,
      "tx": null
    },
    {
      "token": "Elon Mask",
      "symbol": "MASK",
      "address": "HmmgEUdfaGYS7puA987BRFaCn2seZzgovTR8PxS1pump",
      "label": "STRONG BUY",
      "score": 70,
      "tech_score": 48,
      "narr_bonus": 22,
      "narrative": "\ud83c\udfdb\ufe0f PolitiFi",
      "all_narratives": [
        "\ud83c\udfdb\ufe0f PolitiFi"
      ],
      "price": 1.582e-05,
      "change_1h": 71.38,
      "liquidity": 9947.82,
      "volume_1h": 17972.59,
      "mcap": 15820.0,
      "dex_url": "https://dexscreener.com/solana/fpp6wfjpdjnifxppaep89e1jug3qrxkqeqhor4nlvyap",
      "time": "14:41:51",
      "date": "2026-05-07",
      "traded": false,
      "tx": null
    },
    {
      "token": "1 SOL and a Dream",
      "symbol": "1SOL",
      "address": "3qDzKJ1mVz4ZEMKXbVr5XAUV3ot9qNbcfnfBhucf4YtT",
      "label": "WATCH",
      "score": 48,
      "tech_score": 38,
      "narr_bonus": 10,
      "narrative": "\ud83d\udcb0 DeFi",
      "all_narratives": [
        "\ud83d\udcb0 DeFi"
      ],
      "price": 3.332e-05,
      "change_1h": 13.81,
      "liquidity": 15777.45,
      "volume_1h": 627.21,
      "mcap": 33034.0,
      "dex_url": "https://dexscreener.com/solana/2df4aqgucuutcfzzuomik4rzz5vcnatsh5pvfrzqghac",
      "time": "14:41:51",
      "date": "2026-05-07",
      "traded": false,
      "tx": null
    },
    {
      "token": "ELON COIN",
      "symbol": "$ELN",
      "address": "5gTtEjivUTPz8fGxPA7M1KosSi3rkXqhLQGvVgCWnwoR",
      "label": "WATCH",
      "score": 35,
      "tech_score": 13,
      "narr_bonus": 22,
      "narrative": "\ud83c\udfdb\ufe0f PolitiFi",
      "all_narratives": [
        "\ud83c\udfdb\ufe0f PolitiFi",
        "\ud83d\udcb0 DeFi"
      ],
      "price": 1.938e-08,
      "change_1h": 15.5,
      "liquidity": 579.19,
      "volume_1h": 1198.63,
      "mcap": 9689.0,
      "dex_url": "https://dexscreener.com/solana/gfjo6h7xxwuhq6adqwbqynaxz7awdvn4xsbnhx8wfkdc",
      "time": "14:41:52",
      "date": "2026-05-07",
      "traded": false,
      "tx": null
    },
    {
      "token": "Telegram",
      "symbol": "TG",
      "address": "3SDjJTCS9WydzNFPzGUt7PPsHKMHXE1yrEzbHtEkgsCs",
      "label": "WATCH",
      "score": 22,
      "tech_score": 22,
      "narr_bonus": 0,
      "narrative": null,
      "all_narratives": [],
      "price": 1.789e-05,
      "change_1h": 1.61,
      "liquidity": 11265.43,
      "volume_1h": 1604.2,
      "mcap": 17621.0,
      "dex_url": "https://dexscreener.com/solana/9e1rqysezbgnqnwqqhqucssvbta6skso8kwoymzdoqvy",
      "time": "14:41:52",
      "date": "2026-05-07",
      "traded": false,
      "tx": null
    },
    {
      "token": "UFO: Disclosure ",
      "symbol": "UFO",
      "address": "Gps4KFPSP9WckatkZK95SYbmH3m9EfnTYdj3pcCbpump",
      "label": "WATCH",
      "score": 23,
      "tech_score": 23,
      "narr_bonus": 0,
      "narrative": null,
      "all_narratives": [],
      "price": 3.258e-05,
      "change_1h": 11.78,
      "liquidity": 14218.26,
      "volume_1h": 7674.01,
      "mcap": 32587.0,
      "dex_url": "https://dexscreener.com/solana/12vmcaa7hgciuetkkxkdeua2ajk9engj3uz6ylhg1qaw",
      "time": "14:41:52",
      "date": "2026-05-07",
      "traded": false,
      "tx": null
    },
    {
      "token": "patient zero",
      "symbol": "leo",
      "address": "2KRjCQUefvCm7KZCgRRiT82789VWWkNyWjR67W1Epump",
      "label": "WATCH",
      "score": 43,
      "tech_score": 43,
      "narr_bonus": 0,
      "narrative": null,
      "all_narratives": [],
      "price": 6.399e-05,
      "change_1h": 73.87,
      "liquidity": 20203.65,
      "volume_1h": 68678.89,
      "mcap": 63993.0,
      "dex_url": "https://dexscreener.com/solana/h6fp8gle3dpe8i7vmwdfgs6mpcgzfh6rklvfinheeqxd",
      "time": "12:01:16",
      "date": "2026-05-07",
      "traded": false,
      "tx": null
    },
    {
      "token": "SAM BEGMAN",
      "symbol": "SAM BEGMAN",
      "address": "FqYGgWGzCz6gJHvcJPY39L91r2K7qMrpovc5pUaPpump",
      "label": "WATCH",
      "score": 47,
      "tech_score": 29,
      "narr_bonus": 18,
      "narrative": "\ud83d\ude80 Pump.fun",
      "all_narratives": [
        "\ud83d\ude80 Pump.fun"
      ],
      "price": 0.0003292,
      "change_1h": 8.36,
      "liquidity": 46653.76,
      "volume_1h": 98131.43,
      "mcap": 329239.0,
      "dex_url": "https://dexscreener.com/solana/3mo6mwbgyhhn6zitnbn2fmzfla7azawmaywc9grmrxia",
      "time": "12:01:16",
      "date": "2026-05-07",
      "traded": false,
      "tx": null
    },
    {
      "token": "Hantavirus",
      "symbol": "HANTA",
      "address": "F7WCQWh2SUQaPXDUcgnA9rJwU2ZVRBFzCkF5kVAEpump",
      "label": "BUY",
      "score": 63,
      "tech_score": 63,
      "narr_bonus": 0,
      "narrative": null,
      "all_narratives": [],
      "price": 0.0001232,
      "change_1h": 216.0,
      "liquidity": 28632.91,
      "volume_1h": 251796.36,
      "mcap": 123245.0,
      "dex_url": "https://dexscreener.com/solana/bcrckcnoqdrcpfbpfuahp61bnxtnnmbcxndfrko5d3dr",
      "time": "12:01:17",
      "date": "2026-05-07",
      "traded": false,
      "tx": null
    },
    {
      "token": "KAPA",
      "symbol": "KAPA",
      "address": "F4NGyMJHodXyawSwMUgntUVafFjLm1hgGVjctNQ9WNDy",
      "label": "WATCH",
      "score": 37,
      "tech_score": 37,
      "narr_bonus": 0,
      "narrative": null,
      "all_narratives": [],
      "price": 2.212e-06,
      "change_1h": 44.6,
      "liquidity": 1748.39,
      "volume_1h": 139.82,
      "mcap": 2213.0,
      "dex_url": "https://dexscreener.com/solana/6eewygeubgjadu1z7pzpvmxtidgaukpqgcwdhch32clh",
      "time": "12:01:17",
      "date": "2026-05-07",
      "traded": false,
      "tx": null
    },
    {
      "token": "MEMES IN BLACK",
      "symbol": "MIB",
      "address": "reaaHQZfKRiL6U7CpjitAS2GAi88MpUbzyfSCkepump",
      "label": "WATCH",
      "score": 34,
      "tech_score": 22,
      "narr_bonus": 12,
      "narrative": "\ud83d\ude02 Meme Culture",
      "all_narratives": [
        "\ud83d\ude02 Meme Culture"
      ],
      "price": 7.117e-05,
      "change_1h": 4.78,
      "liquidity": 21788.42,
      "volume_1h": 3314.65,
      "mcap": 71173.0,
      "dex_url": "https://dexscreener.com/solana/2zgqx959ktvuy4gqfl3rvsdmbhufpbdgnfb5oevjqye3",
      "time": "12:01:18",
      "date": "2026-05-07",
      "traded": false,
      "tx": null
    },
    {
      "token": "Bull",
      "symbol": "BULL",
      "address": "3TYgKwkE2Y3rxdw9osLRSpxpXmSC1C1oo19W9KHspump",
      "label": "WATCH",
      "score": 41,
      "tech_score": 21,
      "narr_bonus": 20,
      "narrative": "\ud83d\udc3e Animal",
      "all_narratives": [
        "\ud83d\udc3e Animal"
      ],
      "price": 0.004466,
      "change_1h": 4.86,
      "liquidity": 293964.51,
      "volume_1h": 40269.18,
      "mcap": 4466576.0,
      "dex_url": "https://dexscreener.com/solana/hngjllzkwx2mnwhwdkfycmowz8fth2bxxdpj1vbvkjnb",
      "time": "12:01:18",
      "date": "2026-05-07",
      "traded": false,
      "tx": null
    }
  ],
  "trades": [],
  "stats": {
    "scans": 844,
    "signals": 4779,
    "trades": 0
  },
  "wallet": {
    "address": "",
    "balance": 0.2
  },
  "last_scan": "2026-05-07 20:58:18 UTC"
}