{
  "signals": [
    {
      "token": "Pokemon strategy",
      "symbol": "PKMN",
      "address": "WHSQkWSUVtsYj4L2XTryaA27rgjBEssMn6TbGRfPKMN",
      "label": "BUY",
      "score": 63,
      "tech_score": 63,
      "narr_bonus": 0,
      "narrative": null,
      "all_narratives": [],
      "price": 0.0001386,
      "change_1h": 255.0,
      "liquidity": 29293.38,
      "volume_1h": 224754.71,
      "mcap": 138672.0,
      "dex_url": "https://dexscreener.com/solana/2r896pfqzdsmnhyvfefyav3v6l1dlkvh2usmgpvqad9h",
      "time": "22:43:30",
      "date": "2026-05-12",
      "traded": false,
      "tx": null
    },
    {
      "token": "VIRION",
      "symbol": "VIRION",
      "address": "3Zi5hSj5tHUt5MkgmwkL2JXET1sz97YU3XJU3a82pump",
      "label": "STRONG BUY",
      "score": 83,
      "tech_score": 83,
      "narr_bonus": 0,
      "narrative": null,
      "all_narratives": [],
      "price": 0.0003064,
      "change_1h": 590.0,
      "liquidity": 47695.15,
      "volume_1h": 1087565.83,
      "mcap": 306455.0,
      "dex_url": "https://dexscreener.com/solana/cgj1guu4t1se8qt8qvkygxqb1uqztrhtipk5ufzzn4ys",
      "time": "22:43:30",
      "date": "2026-05-12",
      "traded": false,
      "tx": null
    },
    {
      "token": "Monty-Aaron",
      "symbol": "Monty-Aaron",
      "address": "6aztCndC8EZwD9KmHjL2WWezCx1ZhQnavLG3ZrEtpump",
      "label": "STRONG BUY",
      "score": 73,
      "tech_score": 73,
      "narr_bonus": 0,
      "narrative": null,
      "all_narratives": [],
      "price": 0.0001779,
      "change_1h": 356.0,
      "liquidity": 36503.57,
      "volume_1h": 1127883.43,
      "mcap": 177982.0,
      "dex_url": "https://dexscreener.com/solana/e4w9fsbstg1e3zdfegbtifevxeqrxcwzexaixh5uxb8h",
      "time": "22:43:31",
      "date": "2026-05-12",
      "traded": false,
      "tx": null
    },
    {
      "token": "DIAMOND HANDS",
      "symbol": "DIAMOND",
      "address": "B5jkQN49W6oSWThPZu9y7HsgkabBawA7vxHJ3bpcpump",
      "label": "BUY",
      "score": 66,
      "tech_score": 66,
      "narr_bonus": 0,
      "narrative": null,
      "all_narratives": [],
      "price": 0.0004052,
      "change_1h": 107.0,
      "liquidity": 61970.01,
      "volume_1h": 5907950.82,
      "mcap": 405245.0,
      "dex_url": "https://dexscreener.com/solana/ajygdeqszcrrdo7zzrbyikz1asrjpjqdavzn41qqxgwl",
      "time": "22:43:32",
      "date": "2026-05-12",
      "traded": false,
      "tx": null
    },
    {
      "token": "Track Hantavirus",
      "symbol": "TrackHanta",
      "address": "Dagi5mNUCkrTA8p225LFY1TxxMk5po8Mj1aCyeWCpump",
      "label": "WATCH",
      "score": 22,
      "tech_score": 22,
      "narr_bonus": 0,
      "narrative": null,
      "all_narratives": [],
      "price": 2.745e-05,
      "change_1h": 0.94,
      "liquidity": 14772.63,
      "volume_1h": 6834.05,
      "mcap": 27441.0,
      "dex_url": "https://dexscreener.com/solana/8nba1kizsxedsh8f5nkhwlffxjt1jkhn2hiqjgz2c8vn",
      "time": "22:43:32",
      "date": "2026-05-12",
      "traded": false,
      "tx": null
    },
    {
      "token": "this is a special memecoin",
      "symbol": "TISM",
      "address": "DnPA3vTmXVWHzUV4XcFsRK84Af9XmZfcCdB8eitjpump",
      "label": "WATCH",
      "score": 46,
      "tech_score": 34,
      "narr_bonus": 12,
      "narrative": "\ud83d\ude02 Meme Culture",
      "all_narratives": [
        "\ud83d\ude02 Meme Culture",
        "\ud83d\udcb0 DeFi"
      ],
      "price": 5.745e-06,
      "change_1h": 11.94,
      "liquidity": 7498.13,
      "volume_1h": 536.27,
      "mcap": 5320.0,
      "dex_url": "https://dexscreener.com/solana/ggcqjhpwqwctbaqehlutrjnngwfznyp6sae5nm1xb9pt",
      "time": "22:43:32",
      "date": "2026-05-12",
      "traded": false,
      "tx": null
    },
    {
      "token": "LARPGOD",
      "symbol": "LARPGOD",
      "address": "7cfnkmquW2WkCjHcfPuVySQmBTbV3GLUqLg8digLpump",
      "label": "BUY",
      "score": 62,
      "tech_score": 44,
      "narr_bonus": 18,
      "narrative": "\ud83d\ude80 Pump.fun",
      "all_narratives": [
        "\ud83d\ude80 Pump.fun"
      ],
      "price": 9.697e-05,
      "change_1h": 9.06,
      "liquidity": 25946.8,
      "volume_1h": 30745.55,
      "mcap": 96971.0,
      "dex_url": "https://dexscreener.com/solana/2ccehrbcekucphagte5qxabes9znsnrtf9h72lzykwjb",
      "time": "22:43:33",
      "date": "2026-05-12",
      "traded": false,
      "tx": null
    },
    {
      "token": "DIAMOND HANDS",
      "symbol": "DIAMOND",
      "address": "B5jkQN49W6oSWThPZu9y7HsgkabBawA7vxHJ3bpcpump",
      "label": "BUY",
      "score": 56,
      "tech_score": 56,
      "narr_bonus": 0,
      "narrative": null,
      "all_narratives": [],
      "price": 9.892e-05,
      "change_1h": 154.0,
      "liquidity": 26476.95,
      "volume_1h": 331476.36,
      "mcap": 98926.0,
      "dex_url": "https://dexscreener.com/solana/ajygdeqszcrrdo7zzrbyikz1asrjpjqdavzn41qqxgwl",
      "time": "21:37:14",
      "date": "2026-05-12",
      "traded": false,
      "tx": null
    },
    {
      "token": "Strategic American Oil Supply",
      "symbol": "SAOS",
      "address": "SAoSScgqHPW9UFfeEa5SW3tRdUAosD2XGVRAdHiEAL7",
      "label": "STRONG BUY",
      "score": 70,
      "tech_score": 48,
      "narr_bonus": 22,
      "narrative": "\ud83c\udfdb\ufe0f PolitiFi",
      "all_narratives": [
        "\ud83c\udfdb\ufe0f PolitiFi"
      ],
      "price": 8.859e-05,
      "change_1h": 81.83,
      "liquidity": 24778.81,
      "volume_1h": 230710.25,
      "mcap": 88596.0,
      "dex_url": "https://dexscreener.com/solana/7bzcpbdkajj1tz9la1ypzg7sbzgg7xwjrsoya9lvqvdw",
      "time": "21:37:15",
      "date": "2026-05-12",
      "traded": false,
      "tx": null
    },
    {
      "token": "gen z social team",
      "symbol": "genz",
      "address": "h8aN5bPGMxe1P9j4duNDwRHd4xfF22xren56BmZpump",
      "label": "WATCH",
      "score": 35,
      "tech_score": 35,
      "narr_bonus": 0,
      "narrative": null,
      "all_narratives": [],
      "price": 4.791e-05,
      "change_1h": 23.19,
      "liquidity": 17895.97,
      "volume_1h": 17522.11,
      "mcap": 47918.0,
      "dex_url": "https://dexscreener.com/solana/6wsfw3e6wr6vxdkwm6ejmkf6s9ek8slssfee5otqag7h",
      "time": "21:37:16",
      "date": "2026-05-12",
      "traded": false,
      "tx": null
    },
    {
      "token": "Strategic American Oil Supply",
      "symbol": "SAOS",
      "address": "CMButZqQKoRabRAwemmG9gpXKa62KpQByLwjQLbjM1US",
      "label": "BUY",
      "score": 55,
      "tech_score": 33,
      "narr_bonus": 22,
      "narrative": "\ud83c\udfdb\ufe0f PolitiFi",
      "all_narratives": [
        "\ud83c\udfdb\ufe0f PolitiFi"
      ],
      "price": 0.002157,
      "change_1h": 6.59,
      "liquidity": 124645.46,
      "volume_1h": 33508.58,
      "mcap": 2157846.0,
      "dex_url": "https://dexscreener.com/solana/bhvfo9nca9x45yuua7qgwukr4mzcaop2kytsnhmqis4c",
      "time": "21:37:16",
      "date": "2026-05-12",
      "traded": false,
      "tx": null
    },
    {
      "token": "LARPGOD",
      "symbol": "LARPGOD",
      "address": "7cfnkmquW2WkCjHcfPuVySQmBTbV3GLUqLg8digLpump",
      "label": "BUY",
      "score": 51,
      "tech_score": 33,
      "narr_bonus": 18,
      "narrative": "\ud83d\ude80 Pump.fun",
      "all_narratives": [
        "\ud83d\ude80 Pump.fun"
      ],
      "price": 8.716e-05,
      "change_1h": 0.63,
      "liquidity": 24533.1,
      "volume_1h": 22702.87,
      "mcap": 87166.0,
      "dex_url": "https://dexscreener.com/solana/2ccehrbcekucphagte5qxabes9znsnrtf9h72lzykwjb",
      "time": "21:37:17",
      "date": "2026-05-12",
      "traded": false,
      "tx": null
    },
    {
      "token": "PVE COIN",
      "symbol": "PVE",
      "address": "G73g9NsYGA55Dq78jqVuLZenfEPKdQP14gd3atuqpump",
      "label": "STRONG BUY",
      "score": 73,
      "tech_score": 63,
      "narr_bonus": 10,
      "narrative": "\ud83d\udcb0 DeFi",
      "all_narratives": [
        "\ud83d\udcb0 DeFi"
      ],
      "price": 0.0001402,
      "change_1h": 255.0,
      "liquidity": 30710.88,
      "volume_1h": 95046.86,
      "mcap": 70121.0,
      "dex_url": "https://dexscreener.com/solana/bvcmsjxeswvrrfsqphetog8sdy7judxzjjxgumhksy4v",
      "time": "20:04:17",
      "date": "2026-05-12",
      "traded": false,
      "tx": null
    },
    {
      "token": "POPO",
      "symbol": "POPO",
      "address": "DhouzHHr16zJcqzpoGNuG7gi9Mk9vMTPfqpSZtFpump",
      "label": "WATCH",
      "score": 40,
      "tech_score": 40,
      "narr_bonus": 0,
      "narrative": null,
      "all_narratives": [],
      "price": 5.506e-05,
      "change_1h": 24.27,
      "liquidity": 19262.3,
      "volume_1h": 50532.7,
      "mcap": 55069.0,
      "dex_url": "https://dexscreener.com/solana/3gu7yyaeuabwwgnvxpygqpgf1pyviftuxfwunyl3skgf",
      "time": "20:04:19",
      "date": "2026-05-12",
      "traded": false,
      "tx": null
    },
    {
      "token": "No Guy",
      "symbol": "NOGUY",
      "address": "Dk2wjQhBn9sxpMgZHTMriYZsZCXieXVexUzvh13spump",
      "label": "BUY",
      "score": 59,
      "tech_score": 59,
      "narr_bonus": 0,
      "narrative": null,
      "all_narratives": [],
      "price": 0.00188,
      "change_1h": 87.86,
      "liquidity": 117422.1,
      "volume_1h": 373825.8,
      "mcap": 1880018.0,
      "dex_url": "https://dexscreener.com/solana/dqshbipfpa7kx2jnvjecvtxhlf7g1uz4stauammcwlqt",
      "time": "20:04:19",
      "date": "2026-05-12",
      "traded": false,
      "tx": null
    },
    {
      "token": "TROLNALDO",
      "symbol": "TROLNALDO",
      "address": "45pYwARFdL9Y5iUY8tdwWNi2xLDgtauGQPDQyGffpump",
      "label": "BUY",
      "score": 51,
      "tech_score": 51,
      "narr_bonus": 0,
      "narrative": null,
      "all_narratives": [],
      "price": 0.0001042,
      "change_1h": 168.0,
      "liquidity": 26588.36,
      "volume_1h": 98957.24,
      "mcap": 104271.0,
      "dex_url": "https://dexscreener.com/solana/ale8wadbcwhkuqzuwkphq4wrza9njjuhk5uagqihf4tt",
      "time": "20:04:19",
      "date": "2026-05-12",
      "traded": false,
      "tx": null
    },
    {
      "token": "Compute Coin",
      "symbol": "COMPUTE",
      "address": "AfV8U7ZSbdg4ZM5xZ2P9vbrfX3NmEBSDYNNuBriQpump",
      "label": "STRONG BUY",
      "score": 78,
      "tech_score": 68,
      "narr_bonus": 10,
      "narrative": "\ud83d\udcb0 DeFi",
      "all_narratives": [
        "\ud83d\udcb0 DeFi"
      ],
      "price": 0.0002279,
      "change_1h": 996.0,
      "liquidity": 40056.61,
      "volume_1h": 470147.83,
      "mcap": 227958.0,
      "dex_url": "https://dexscreener.com/solana/ddlisrxatmu34u3u573yywm8w8dbjazgbatzpt9uc7fl",
      "time": "20:04:20",
      "date": "2026-05-12",
      "traded": false,
      "tx": null
    },
    {
      "token": "cardputer ",
      "symbol": "cardputer",
      "address": "4HuTporSb2n91FrmV3Ki6GiUgfAF4QXgcQvaf6dUpump",
      "label": "WATCH",
      "score": 29,
      "tech_score": 29,
      "narr_bonus": 0,
      "narrative": null,
      "all_narratives": [],
      "price": 2.31e-05,
      "change_1h": 15.17,
      "liquidity": 12510.0,
      "volume_1h": 71086.38,
      "mcap": 23108.0,
      "dex_url": "https://dexscreener.com/solana/ajjyzdfvbpzlhq2blyjvvwja9pydxmmhh1w3yajh1tv2",
      "time": "20:04:21",
      "date": "2026-05-12",
      "traded": false,
      "tx": null
    },
    {
      "token": "Predictr",
      "symbol": "Predictr",
      "address": "6SQgSubdpAXfxaTrsYYoAJMUJLua4C6aGNNMr5C9pump",
      "label": "WATCH",
      "score": 48,
      "tech_score": 48,
      "narr_bonus": 0,
      "narrative": null,
      "all_narratives": [],
      "price": 0.0002292,
      "change_1h": 82.26,
      "liquidity": 40386.13,
      "volume_1h": 436536.0,
      "mcap": 229292.0,
      "dex_url": "https://dexscreener.com/solana/aadyxt41kzroy82cwf1kkjfmv8t1beltmwuwacsmpkku",
      "time": "20:04:21",
      "date": "2026-05-12",
      "traded": false,
      "tx": null
    },
    {
      "token": "Royal Flop",
      "symbol": "flop",
      "address": "3C4qPgC33dJETyxA3Jz2zXpDbetWdDd66aLdhGrEpump",
      "label": "WATCH",
      "score": 48,
      "tech_score": 48,
      "narr_bonus": 0,
      "narrative": null,
      "all_narratives": [],
      "price": 8.53e-05,
      "change_1h": 63.0,
      "liquidity": 24364.74,
      "volume_1h": 179500.07,
      "mcap": 85307.0,
      "dex_url": "https://dexscreener.com/solana/3ajgumeqzbcuetewwigkkqe4rbzbem1smeg24ijemxgs",
      "time": "20:04:21",
      "date": "2026-05-12",
      "traded": false,
      "tx": null
    },
    {
      "token": "Green Kitten Crew",
      "symbol": "GKC",
      "address": "GPXY56UALMCnKkbPnWKRdEeG6DWvbFafySsG48MRpump",
      "label": "BUY",
      "score": 65,
      "tech_score": 50,
      "narr_bonus": 15,
      "narrative": "\ud83d\udc65 Community",
      "all_narratives": [
        "\ud83d\udc65 Community"
      ],
      "price": 0.0001897,
      "change_1h": 20.99,
      "liquidity": 40634.8,
      "volume_1h": 33259.1,
      "mcap": 185561.0,
      "dex_url": "https://dexscreener.com/solana/44gjhjvgyz3okzlf9lzn2xf7a8yrqm9ecikcjlvcuezv",
      "time": "20:04:22",
      "date": "2026-05-12",
      "traded": false,
      "tx": null
    },
    {
      "token": "Kevun Wersh",
      "symbol": "KEVUN",
      "address": "DXwcaZ3atb4WfrzDtkR3EcRhkv2rrbzjKLQxyPjNpump",
      "label": "WATCH",
      "score": 25,
      "tech_score": 25,
      "narr_bonus": 0,
      "narrative": null,
      "all_narratives": [],
      "price": 8.946e-05,
      "change_1h": 2.88,
      "liquidity": 25679.8,
      "volume_1h": 49751.81,
      "mcap": 89449.0,
      "dex_url": "https://dexscreener.com/solana/8bxem9xngbilu6zs4iyaguvjewxqja5kjydlcleeucpc",
      "time": "20:04:22",
      "date": "2026-05-12",
      "traded": false,
      "tx": null
    },
    {
      "token": "had to take profits sir",
      "symbol": "https",
      "address": "7sGdNQSvUGpahh6qyXB3g5gsdK9FAzZM299KyCXspump",
      "label": "WATCH",
      "score": 26,
      "tech_score": 26,
      "narr_bonus": 0,
      "narrative": null,
      "all_narratives": [],
      "price": 0.0001803,
      "change_1h": 5.66,
      "liquidity": 53077.62,
      "volume_1h": 3373.19,
      "mcap": 180285.0,
      "dex_url": "https://dexscreener.com/solana/amk2hphohkte2tcjwkbfmpyr3jimds3j19xgdhx4zclk",
      "time": "20:04:23",
      "date": "2026-05-12",
      "traded": false,
      "tx": null
    },
    {
      "token": "EPIC FACE",
      "symbol": "EPIC",
      "address": "4XEtVrvHEnik8Gs4b3spWUuwZiJ1tc3fQxBYgvCrpump",
      "label": "WATCH",
      "score": 45,
      "tech_score": 45,
      "narr_bonus": 0,
      "narrative": null,
      "all_narratives": [],
      "price": 4.744e-05,
      "change_1h": 21.91,
      "liquidity": 17862.52,
      "volume_1h": 105393.03,
      "mcap": 47450.0,
      "dex_url": "https://dexscreener.com/solana/fa2a9hvvrrm5prf7p5wme8ten5a8cmjjyrds4zscrwmv",
      "time": "17:59:44",
      "date": "2026-05-12",
      "traded": false,
      "tx": null
    },
    {
      "token": "LMAO!",
      "symbol": "LMAO!",
      "address": "H74CYmXgMkYHYuSRsZt6RJb4NYp2u72Vw8BS5huApump",
      "label": "WATCH",
      "score": 10,
      "tech_score": 10,
      "narr_bonus": 0,
      "narrative": null,
      "all_narratives": [],
      "price": 0.003058,
      "change_1h": 3.83,
      "liquidity": 279139.08,
      "volume_1h": 8312.02,
      "mcap": 3057295.0,
      "dex_url": "https://dexscreener.com/solana/afayrfh7huynkv5mbvbnrhwx29m9jzul3ysgtqz69auv",
      "time": "17:59:45",
      "date": "2026-05-12",
      "traded": false,
      "tx": null
    },
    {
      "token": "Andes Virus",
      "symbol": "ANDV",
      "address": "jvKtLFLnNGPM7edS9KEpYqPxuY8HPGTZohLFM4Spump",
      "label": "WATCH",
      "score": 35,
      "tech_score": 35,
      "narr_bonus": 0,
      "narrative": null,
      "all_narratives": [],
      "price": 0.0004253,
      "change_1h": 37.39,
      "liquidity": 64346.34,
      "volume_1h": 88552.6,
      "mcap": 425349.0,
      "dex_url": "https://dexscreener.com/solana/jhmcrrlmpte1qvypwe1yjtjzm2k44eorpducj6j8pwc",
      "time": "17:59:45",
      "date": "2026-05-12",
      "traded": false,
      "tx": null
    },
    {
      "token": "Ridiculous Money Glitch",
      "symbol": "RMG",
      "address": "rmgSDMYX5e1ySoxjnai8QpmVuRVCAcwXaXxHfUC7AxN",
      "label": "BUY",
      "score": 50,
      "tech_score": 40,
      "narr_bonus": 10,
      "narrative": "\ud83d\udcb0 DeFi",
      "all_narratives": [
        "\ud83d\udcb0 DeFi"
      ],
      "price": 2.195e-05,
      "change_1h": 25.25,
      "liquidity": 8618.76,
      "volume_1h": 1263.0,
      "mcap": 21956.0,
      "dex_url": "https://dexscreener.com/solana/g7yrneqh76eu14j113ac9mvtsrde3k49q1znztfjvsei",
      "time": "17:59:45",
      "date": "2026-05-12",
      "traded": false,
      "tx": null
    },
    {
      "token": "Ollight",
      "symbol": "Ollight",
      "address": "HmZWJymp357ReTz5ydxwx9f6hkhxNScxQKT6yfGDSxq8",
      "label": "WATCH",
      "score": 34,
      "tech_score": 34,
      "narr_bonus": 0,
      "narrative": null,
      "all_narratives": [],
      "price": 1.621e-10,
      "change_1h": 8.55,
      "liquidity": 9372.06,
      "volume_1h": 401.14,
      "mcap": 16214.0,
      "dex_url": "https://dexscreener.com/solana/8jqvkeqa5qwtgbjumfhvelr5tnbedmm8miak2sgq2zxw",
      "time": "17:59:46",
      "date": "2026-05-12",
      "traded": false,
      "tx": null
    },
    {
      "token": "Ultraterrestrials ",
      "symbol": "P47-P52",
      "address": "HuzTc6Um24A1nTvertbNQv3pp8HxEVSoKB614Arfpump",
      "label": "WATCH",
      "score": 31,
      "tech_score": 31,
      "narr_bonus": 0,
      "narrative": null,
      "all_narratives": [],
      "price": 3.932e-06,
      "change_1h": 9.5,
      "liquidity": 5140.56,
      "volume_1h": 2184.24,
      "mcap": 3933.0,
      "dex_url": "https://dexscreener.com/solana/4isbx7edstzpcmftism9qctueu59pbuaigtnd7nn3b9g",
      "time": "17:59:46",
      "date": "2026-05-12",
      "traded": false,
      "tx": null
    },
    {
      "token": "TROLLOPOOP",
      "symbol": "TROLLOPOOP",
      "address": "AFaycnPrFsLbHNQKRpXdUzUcsKFENWwkzvSSSToCpump",
      "label": "WATCH",
      "score": 41,
      "tech_score": 41,
      "narr_bonus": 0,
      "narrative": null,
      "all_narratives": [],
      "price": 0.001061,
      "change_1h": 27.44,
      "liquidity": 110919.85,
      "volume_1h": 972563.39,
      "mcap": 1061815.0,
      "dex_url": "https://dexscreener.com/solana/8oftava6wddfyvkwbdn1ibxdoplpxran5qs9xi8rgekm",
      "time": "17:59:46",
      "date": "2026-05-12",
      "traded": false,
      "tx": null
    },
    {
      "token": "APification",
      "symbol": "AP",
      "address": "9PqAmXKg2vYkATnHwm4cVy4sqLkhLj5WFchW1Bzbpump",
      "label": "BUY",
      "score": 55,
      "tech_score": 35,
      "narr_bonus": 20,
      "narrative": "\ud83d\udc3e Animal",
      "all_narratives": [
        "\ud83d\udc3e Animal"
      ],
      "price": 1.519e-05,
      "change_1h": 44.45,
      "liquidity": 10064.43,
      "volume_1h": 20681.62,
      "mcap": 14042.0,
      "dex_url": "https://dexscreener.com/solana/3m4aawfkm5upgdeqxc6fyjryzczjxn1kswogxjantag4",
      "time": "15:56:23",
      "date": "2026-05-12",
      "traded": false,
      "tx": null
    },
    {
      "token": "Narrative Sniper",
      "symbol": "SNIPER",
      "address": "DsJN86Gv5RHoAs9KXinA8bZdoJhC1bcKXj3VQtX6pump",
      "label": "WATCH",
      "score": 35,
      "tech_score": 35,
      "narr_bonus": 0,
      "narrative": null,
      "all_narratives": [],
      "price": 5.041e-05,
      "change_1h": 30.53,
      "liquidity": 18444.3,
      "volume_1h": 95151.05,
      "mcap": 50410.0,
      "dex_url": "https://dexscreener.com/solana/f46zu5mjaz5gudz1qvxjvmcxttd5qrgdiur9f7xyrhdm",
      "time": "15:56:24",
      "date": "2026-05-12",
      "traded": false,
      "tx": null
    },
    {
      "token": "Ape",
      "symbol": "Ape",
      "address": "2kKsFHyLX7e6SFPJq3FqTgvsyiopUH22XXXPbLi3pump",
      "label": "STRONG BUY",
      "score": 76,
      "tech_score": 56,
      "narr_bonus": 20,
      "narrative": "\ud83d\udc3e Animal",
      "all_narratives": [
        "\ud83d\udc3e Animal",
        "\ud83d\ude80 Pump.fun"
      ],
      "price": 8.926e-05,
      "change_1h": 126.0,
      "liquidity": 24727.16,
      "volume_1h": 180918.78,
      "mcap": 89269.0,
      "dex_url": "https://dexscreener.com/solana/bdknpx5duecwxygbks5pwwggckhwqsqaf58qsmjmjctx",
      "time": "15:56:24",
      "date": "2026-05-12",
      "traded": false,
      "tx": null
    },
    {
      "token": "K9",
      "symbol": "K9",
      "address": "5je5ondjVJcHjWz2v4mLZn7PsQGr47XQFjFTfrtCu1ox",
      "label": "WATCH",
      "score": 47,
      "tech_score": 47,
      "narr_bonus": 0,
      "narrative": null,
      "all_narratives": [],
      "price": 0.0003121,
      "change_1h": 30.33,
      "liquidity": 28675.2,
      "volume_1h": 12004.56,
      "mcap": 350530.0,
      "dex_url": "https://dexscreener.com/solana/szchbrcfoucr3xzuhqtngzxcr2dunvurd5htx9ntxzb",
      "time": "15:56:25",
      "date": "2026-05-12",
      "traded": false,
      "tx": null
    },
    {
      "token": "shitty house",
      "symbol": "SHITTYHOUSE",
      "address": "2hkbMF2J3Nif19AkdoE1WFTyS8XTUHGdC857CDkKpump",
      "label": "WATCH",
      "score": 49,
      "tech_score": 27,
      "narr_bonus": 22,
      "narrative": "\ud83c\udfdb\ufe0f PolitiFi",
      "all_narratives": [
        "\ud83c\udfdb\ufe0f PolitiFi"
      ],
      "price": 1.004e-05,
      "change_1h": 43.92,
      "liquidity": 8183.59,
      "volume_1h": 14600.96,
      "mcap": 10046.0,
      "dex_url": "https://dexscreener.com/solana/askkh8gcaxwrvceuac1aenpprzsmjmdxwqgsqdk9pcnu",
      "time": "15:56:26",
      "date": "2026-05-12",
      "traded": false,
      "tx": null
    },
    {
      "token": "Elienus Muskius",
      "symbol": "ELIENUS",
      "address": "yrKmZe5x2YBp1P6ufKLUCNifPbqxwHiwsbfDRWBpump",
      "label": "WATCH",
      "score": 14,
      "tech_score": 14,
      "narr_bonus": 0,
      "narrative": null,
      "all_narratives": [],
      "price": 5.583e-05,
      "change_1h": 1.48,
      "liquidity": 19842.82,
      "volume_1h": 720.98,
      "mcap": 55823.0,
      "dex_url": "https://dexscreener.com/solana/5gcxz9mq2fx3kfjzcqd9aaa8o1c8qjlsrasqs4ikmk7t",
      "time": "15:56:26",
      "date": "2026-05-12",
      "traded": false,
      "tx": null
    },
    {
      "token": "Baby Tung Tung Tung Sahur",
      "symbol": "BabyT",
      "address": "FDN8ycmEo11HxCssiFZ1nTgdJxyuETvyEc3mD85Hpump",
      "label": "WATCH",
      "score": 18,
      "tech_score": 18,
      "narr_bonus": 0,
      "narrative": null,
      "all_narratives": [],
      "price": 1.768e-05,
      "change_1h": 13.59,
      "liquidity": 10943.98,
      "volume_1h": 1419.27,
      "mcap": 17681.0,
      "dex_url": "https://dexscreener.com/solana/euqmn1cz5puinvvlrgf153n5ftkfmafgmp94dqsyzjxh",
      "time": "15:56:26",
      "date": "2026-05-12",
      "traded": false,
      "tx": null
    },
    {
      "token": "LARPGOD",
      "symbol": "LARPGOD",
      "address": "7cfnkmquW2WkCjHcfPuVySQmBTbV3GLUqLg8digLpump",
      "label": "BUY",
      "score": 53,
      "tech_score": 35,
      "narr_bonus": 18,
      "narrative": "\ud83d\ude80 Pump.fun",
      "all_narratives": [
        "\ud83d\ude80 Pump.fun"
      ],
      "price": 5.607e-05,
      "change_1h": 43.78,
      "liquidity": 19497.35,
      "volume_1h": 74977.92,
      "mcap": 56075.0,
      "dex_url": "https://dexscreener.com/solana/2ccehrbcekucphagte5qxabes9znsnrtf9h72lzykwjb",
      "time": "13:22:43",
      "date": "2026-05-12",
      "traded": false,
      "tx": null
    },
    {
      "token": "Mirumi",
      "symbol": "Mirumi",
      "address": "3BRC7ZfRXXfXNFwYkQr1dJCPNZKDRYc4n7KGwrtzpump",
      "label": "WATCH",
      "score": 30,
      "tech_score": 30,
      "narr_bonus": 0,
      "narrative": null,
      "all_narratives": [],
      "price": 0.0002865,
      "change_1h": 2.74,
      "liquidity": 53539.65,
      "volume_1h": 2074.51,
      "mcap": 285613.0,
      "dex_url": "https://dexscreener.com/solana/a1rwbphpwuytm2ccpq8e4scdxeyyfufy5jikyrhmq696",
      "time": "13:22:45",
      "date": "2026-05-12",
      "traded": false,
      "tx": null
    },
    {
      "token": "TROLLOPOOP",
      "symbol": "TROLLOPOOP",
      "address": "AFaycnPrFsLbHNQKRpXdUzUcsKFENWwkzvSSSToCpump",
      "label": "BUY",
      "score": 63,
      "tech_score": 63,
      "narr_bonus": 0,
      "narrative": null,
      "all_narratives": [],
      "price": 0.0001506,
      "change_1h": 283.0,
      "liquidity": 32496.25,
      "volume_1h": 288849.75,
      "mcap": 150674.0,
      "dex_url": "https://dexscreener.com/solana/8oftava6wddfyvkwbdn1ibxdoplpxran5qs9xi8rgekm",
      "time": "11:30:29",
      "date": "2026-05-12",
      "traded": false,
      "tx": null
    },
    {
      "token": "GRIMLESS",
      "symbol": "GRIM",
      "address": "9fpGNwbUj8zRETtHn3TM4X8w2mi7LKbRkBU3rDt2pump",
      "label": "WATCH",
      "score": 43,
      "tech_score": 43,
      "narr_bonus": 0,
      "narrative": null,
      "all_narratives": [],
      "price": 6.853e-05,
      "change_1h": 70.4,
      "liquidity": 21559.4,
      "volume_1h": 99177.61,
      "mcap": 68539.0,
      "dex_url": "https://dexscreener.com/solana/5mxzwf3fjurvhwpky6ie42ubuttqng38drsrscperwhx",
      "time": "11:30:30",
      "date": "2026-05-12",
      "traded": false,
      "tx": null
    },
    {
      "token": "Spain",
      "symbol": "SPAIN",
      "address": "D2bSDzYKpFCePrp98dfN4uuKH1SBnYiiWjwmpYBspump",
      "label": "BUY",
      "score": 62,
      "tech_score": 37,
      "narr_bonus": 25,
      "narrative": "\ud83e\udd16 AI Agent",
      "all_narratives": [
        "\ud83e\udd16 AI Agent"
      ],
      "price": 4.049e-05,
      "change_1h": 8.83,
      "liquidity": 16451.47,
      "volume_1h": 17127.15,
      "mcap": 40497.0,
      "dex_url": "https://dexscreener.com/solana/fqarato6twpraedipkt6vxu61amir7qmtje78vhcy5p9",
      "time": "11:30:30",
      "date": "2026-05-12",
      "traded": false,
      "tx": null
    },
    {
      "token": "TOMA",
      "symbol": "TOMA",
      "address": "58DSadE1vLnKXi6XCyujra6GKkLwvAaJN63dygoVpump",
      "label": "BUY",
      "score": 61,
      "tech_score": 61,
      "narr_bonus": 0,
      "narrative": null,
      "all_narratives": [],
      "price": 8.646e-05,
      "change_1h": 119.0,
      "liquidity": 25277.25,
      "volume_1h": 644926.0,
      "mcap": 86466.0,
      "dex_url": "https://dexscreener.com/solana/c7b3ak4acuiqsvun4fd5s3rte615bhxbkukrtq9sx61x",
      "time": "11:30:30",
      "date": "2026-05-12",
      "traded": false,
      "tx": null
    },
    {
      "token": "Ker Stemur",
      "symbol": "Ker",
      "address": "Dpse6VGe8eYUiSuikDv5M5JJ86JoWhAm49CyW7V9pump",
      "label": "WATCH",
      "score": 45,
      "tech_score": 45,
      "narr_bonus": 0,
      "narrative": null,
      "all_narratives": [],
      "price": 8.221e-05,
      "change_1h": 36.61,
      "liquidity": 23796.07,
      "volume_1h": 111094.4,
      "mcap": 82206.0,
      "dex_url": "https://dexscreener.com/solana/hbaiv6cwktn3xqch9qcknqfxkt2qzc51rwgzgnm9ujft",
      "time": "11:30:31",
      "date": "2026-05-12",
      "traded": false,
      "tx": null
    },
    {
      "token": "France",
      "symbol": "FRANCE",
      "address": "2gXeM4einZoLMSQ5K7s6rHzCAeksU2hRFouBpqSopump",
      "label": "WATCH",
      "score": 29,
      "tech_score": 29,
      "narr_bonus": 0,
      "narrative": null,
      "all_narratives": [],
      "price": 5.692e-05,
      "change_1h": 8.98,
      "liquidity": 19516.24,
      "volume_1h": 12222.71,
      "mcap": 56924.0,
      "dex_url": "https://dexscreener.com/solana/2zqxohpqtkl26mloqqn8iedorx7m1qy9ahao2yqnjiqf",
      "time": "11:30:31",
      "date": "2026-05-12",
      "traded": false,
      "tx": null
    },
    {
      "token": "Roaring Kitty",
      "symbol": "KITTY",
      "address": "AYzMMaWmk6peDU5D623tWJD6CrnneCH9WYNLJchFBAGS",
      "label": "WATCH",
      "score": 32,
      "tech_score": 32,
      "narr_bonus": 0,
      "narrative": null,
      "all_narratives": [],
      "price": 4.182e-05,
      "change_1h": 39.68,
      "liquidity": 15140.48,
      "volume_1h": 6887.78,
      "mcap": 41811.0,
      "dex_url": "https://dexscreener.com/solana/4im3rcpjc9otad1ys35wrnnamgtqbindwzymtmm6pjvj",
      "time": "11:30:31",
      "date": "2026-05-12",
      "traded": false,
      "tx": null
    },
    {
      "token": "DISCLOSURE",
      "symbol": "DISCLOSURE",
      "address": "FpBhnZLzHjgPrc69vkimPtHCwN4xoeX3RUhDa3Bpump",
      "label": "WATCH",
      "score": 29,
      "tech_score": 29,
      "narr_bonus": 0,
      "narrative": null,
      "all_narratives": [],
      "price": 0.0002429,
      "change_1h": 8.01,
      "liquidity": 42854.05,
      "volume_1h": 35335.01,
      "mcap": 242915.0,
      "dex_url": "https://dexscreener.com/solana/97j7ju8ros5rcp7ue9k3zvaruqxdkgak8eqvwf9aykjf",
      "time": "11:30:32",
      "date": "2026-05-12",
      "traded": false,
      "tx": null
    },
    {
      "token": "micro troll face",
      "symbol": "microtroll",
      "address": "HkU2cMmgYwskAuWj1Z9LAaGZTRBBZUBKTk3DGoXZpump",
      "label": "WATCH",
      "score": 25,
      "tech_score": 25,
      "narr_bonus": 0,
      "narrative": null,
      "all_narratives": [],
      "price": 0.0001347,
      "change_1h": 3.76,
      "liquidity": 30812.6,
      "volume_1h": 63631.81,
      "mcap": 134769.0,
      "dex_url": "https://dexscreener.com/solana/d18pmt1xqgbc6grpezbsidkbvzzeugcadscwetsbxgun",
      "time": "11:30:32",
      "date": "2026-05-12",
      "traded": false,
      "tx": null
    },
    {
      "token": "UFO",
      "symbol": "UFO",
      "address": "4CJiyMRSyHURUMyupcyYfW3wzoiMPNS8aJYngZ799SZx",
      "label": "WATCH",
      "score": 44,
      "tech_score": 44,
      "narr_bonus": 0,
      "narrative": null,
      "all_narratives": [],
      "price": 0.03722,
      "change_1h": 53.39,
      "liquidity": 9137.11,
      "volume_1h": 1353.35,
      "mcap": 37002.0,
      "dex_url": "https://dexscreener.com/solana/dvrxntajgcbl84fdhswz9wqc6o3hubyyf1ohutbasefj",
      "time": "11:30:32",
      "date": "2026-05-12",
      "traded": false,
      "tx": null
    },
    {
      "token": "Pill Gaytes",
      "symbol": "GAYTES",
      "address": "HSznAnNhSFgyRWiZh4m7pBmtjHsSLi4Dbmjp18zppump",
      "label": "WATCH",
      "score": 40,
      "tech_score": 40,
      "narr_bonus": 0,
      "narrative": null,
      "all_narratives": [],
      "price": 0.0003421,
      "change_1h": 31.81,
      "liquidity": 70113.91,
      "volume_1h": 258666.21,
      "mcap": 342142.0,
      "dex_url": "https://dexscreener.com/solana/69vfyvsbzcgfbkiqqwsxmuhaqt2a1zuxyvwzavzpqhvm",
      "time": "11:30:32",
      "date": "2026-05-12",
      "traded": false,
      "tx": null
    }
  ],
  "trades": [],
  "stats": {
    "scans": 920,
    "signals": 5293,
    "trades": 0
  },
  "wallet": {
    "address": "",
    "balance": 0.2
  },
  "last_scan": "2026-05-12 22:43:29 UTC"
}