{
  "signals": [
    {
      "token": "Nyan Cat",
      "symbol": "NYAN",
      "address": "F7ySj1p4f83fLXzdN8Dgf9UySr4MrkPVgZ1usFMzpump",
      "label": "BUY",
      "score": 68,
      "tech_score": 48,
      "narr_bonus": 20,
      "narrative": "\ud83d\udc3e Animal",
      "all_narratives": [
        "\ud83d\udc3e Animal"
      ],
      "price": 5.557e-05,
      "change_1h": 63.1,
      "liquidity": 18914.18,
      "volume_1h": 412859.09,
      "mcap": 55573.0,
      "dex_url": "https://dexscreener.com/solana/6bduhpsp2jahbug2u7nbwsk4qjaeqh26swddxrdntxt2",
      "time": "21:57:20",
      "date": "2026-05-02",
      "traded": false,
      "tx": null
    },
    {
      "token": "SAM MOGMAN",
      "symbol": "SAM MOGMAN",
      "address": "EvmirLpR7d1bLKFAPmndAimac5jYGwwg5Ee31tc7baiN",
      "label": "BUY",
      "score": 63,
      "tech_score": 45,
      "narr_bonus": 18,
      "narrative": "\ud83d\ude80 Pump.fun",
      "all_narratives": [
        "\ud83d\ude80 Pump.fun"
      ],
      "price": 6.026e-05,
      "change_1h": 28.45,
      "liquidity": 19366.7,
      "volume_1h": 203698.75,
      "mcap": 60265.0,
      "dex_url": "https://dexscreener.com/solana/31hhhd2f81lcijsg5lmgcrm7zezzeomb5obqzrs4wlcm",
      "time": "21:57:20",
      "date": "2026-05-02",
      "traded": false,
      "tx": null
    },
    {
      "token": "Max Long",
      "symbol": "ML",
      "address": "DyhgWtTeAE2UYEfLwpAZ4441eaCWFedRMoxUYM9ypump",
      "label": "WATCH",
      "score": 29,
      "tech_score": 29,
      "narr_bonus": 0,
      "narrative": null,
      "all_narratives": [],
      "price": 7.487e-05,
      "change_1h": 19.54,
      "liquidity": 21489.92,
      "volume_1h": 20750.26,
      "mcap": 74781.0,
      "dex_url": "https://dexscreener.com/solana/7p23n7sfxlsz54gyd5sbzdwrbiuvzas9ajss6uvykyrm",
      "time": "21:57:21",
      "date": "2026-05-02",
      "traded": false,
      "tx": null
    },
    {
      "token": "The Lone Wolf",
      "symbol": "ROMEO ",
      "address": "7tzXaxLYLMqphmJuRwyXc9hRAX18awqvFbHbqZRUpump",
      "label": "WATCH",
      "score": 41,
      "tech_score": 21,
      "narr_bonus": 20,
      "narrative": "\ud83d\udc3e Animal",
      "all_narratives": [
        "\ud83d\udc3e Animal"
      ],
      "price": 2.303e-05,
      "change_1h": 10.3,
      "liquidity": 11747.55,
      "volume_1h": 10791.5,
      "mcap": 23034.0,
      "dex_url": "https://dexscreener.com/solana/d34pecdhrc9ipy5wi8fxvzxkw9khygqzcf8bdpe9ni5g",
      "time": "21:57:21",
      "date": "2026-05-02",
      "traded": false,
      "tx": null
    },
    {
      "token": "Unipump",
      "symbol": "UNIPUMP",
      "address": "9KrdYnHHrsWYpWMxyzbmmrjcXRr7ERWpB3byNeb1pump",
      "label": "WATCH",
      "score": 39,
      "tech_score": 21,
      "narr_bonus": 18,
      "narrative": "\ud83d\ude80 Pump.fun",
      "all_narratives": [
        "\ud83d\ude80 Pump.fun"
      ],
      "price": 0.0001758,
      "change_1h": 12.89,
      "liquidity": 38050.21,
      "volume_1h": 43042.72,
      "mcap": 175863.0,
      "dex_url": "https://dexscreener.com/solana/2umb31px1fghb5qlmcjrrdhhdjcrzocwkeghsk4775bf",
      "time": "21:57:21",
      "date": "2026-05-02",
      "traded": false,
      "tx": null
    },
    {
      "token": "Manfred",
      "symbol": "Manfred",
      "address": "2xbBHYkn6v5PGi19EHp9DiDDTjTB1QHKmwgxdQKx4xff",
      "label": "WATCH",
      "score": 32,
      "tech_score": 32,
      "narr_bonus": 0,
      "narrative": null,
      "all_narratives": [],
      "price": 4.826e-05,
      "change_1h": 26.58,
      "liquidity": 17200.55,
      "volume_1h": 8137.87,
      "mcap": 48260.0,
      "dex_url": "https://dexscreener.com/solana/dnezr75pnkgq7wdpywgctvu5yw9aohxa2bdkzsldfshg",
      "time": "21:57:22",
      "date": "2026-05-02",
      "traded": false,
      "tx": null
    },
    {
      "token": "Shakespeare Brah",
      "symbol": "Shakespeare",
      "address": "GejNiJRPK5dTEukkcjFoMDZiEJxquqnZtjNc6k2apump",
      "label": "WATCH",
      "score": 48,
      "tech_score": 48,
      "narr_bonus": 0,
      "narrative": null,
      "all_narratives": [],
      "price": 4.721e-05,
      "change_1h": 93.15,
      "liquidity": 16850.03,
      "volume_1h": 17046.77,
      "mcap": 47211.0,
      "dex_url": "https://dexscreener.com/solana/edbvkqufdwqmxv9yvivpkpmbzsubcl4n8seexjvsvvuf",
      "time": "21:07:58",
      "date": "2026-05-02",
      "traded": false,
      "tx": null
    },
    {
      "token": "Max Long",
      "symbol": "ML",
      "address": "DyhgWtTeAE2UYEfLwpAZ4441eaCWFedRMoxUYM9ypump",
      "label": "WATCH",
      "score": 43,
      "tech_score": 43,
      "narr_bonus": 0,
      "narrative": null,
      "all_narratives": [],
      "price": 6.553e-05,
      "change_1h": 93.9,
      "liquidity": 20015.37,
      "volume_1h": 50020.42,
      "mcap": 65453.0,
      "dex_url": "https://dexscreener.com/solana/7p23n7sfxlsz54gyd5sbzdwrbiuvzas9ajss6uvykyrm",
      "time": "21:07:59",
      "date": "2026-05-02",
      "traded": false,
      "tx": null
    },
    {
      "token": "Angry Trump",
      "symbol": "FURY",
      "address": "3yLxAR1UQub1J1gjodMV9CzrxVgJgksxqMPxJD7NGa3P",
      "label": "STRONG BUY",
      "score": 95,
      "tech_score": 73,
      "narr_bonus": 22,
      "narrative": "\ud83c\udfdb\ufe0f PolitiFi",
      "all_narratives": [
        "\ud83c\udfdb\ufe0f PolitiFi"
      ],
      "price": 0.0001278,
      "change_1h": 7438.0,
      "liquidity": 29899.61,
      "volume_1h": 150839.41,
      "mcap": 127877.0,
      "dex_url": "https://dexscreener.com/solana/zkrcxvgdmsvtjhgezsnsshfbu6v4g4egc9a1pwa5jus",
      "time": "21:07:59",
      "date": "2026-05-02",
      "traded": false,
      "tx": null
    },
    {
      "token": "\u3079\u3053\u301c\u305a",
      "symbol": "Bekozu",
      "address": "Hb3ZsZrd8hkmPmvJyMmGaZrxvdxJFBb3S9La6vsEpump",
      "label": "WATCH",
      "score": 24,
      "tech_score": 24,
      "narr_bonus": 0,
      "narrative": null,
      "all_narratives": [],
      "price": 8.748e-06,
      "change_1h": 48.51,
      "liquidity": 7209.84,
      "volume_1h": 7661.9,
      "mcap": 8748.0,
      "dex_url": "https://dexscreener.com/solana/6gypnhxy8froubhrkrwqcmdlw8auahb1z5hnggxhetdd",
      "time": "21:08:01",
      "date": "2026-05-02",
      "traded": false,
      "tx": null
    },
    {
      "token": "LMEOW",
      "symbol": "LMEOW",
      "address": "3T3ePWvriBnF82Qp8PA8xD9cacVoqatzfuvFxMfLpump",
      "label": "BUY",
      "score": 53,
      "tech_score": 53,
      "narr_bonus": 0,
      "narrative": null,
      "all_narratives": [],
      "price": 0.0001831,
      "change_1h": 90.17,
      "liquidity": 35493.9,
      "volume_1h": 534307.2,
      "mcap": 183132.0,
      "dex_url": "https://dexscreener.com/solana/b7wa7vqp28gx84atehvrne5giwnxrg6egdmx5dsqncuk",
      "time": "21:08:01",
      "date": "2026-05-02",
      "traded": false,
      "tx": null
    },
    {
      "token": "Praxis",
      "symbol": "PRX",
      "address": "9iR8Urs95yLeiajX3T6eYK9t4YBcLbrWS8pCKgoPFb7n",
      "label": "BUY",
      "score": 51,
      "tech_score": 51,
      "narr_bonus": 0,
      "narrative": null,
      "all_narratives": [],
      "price": 0.0004311,
      "change_1h": 108.0,
      "liquidity": 58861.36,
      "volume_1h": 93724.06,
      "mcap": 431176.0,
      "dex_url": "https://dexscreener.com/solana/25xjqz8yvpmvgjyvmys3dyfal4k6hdmvqmxkcprb4vn8",
      "time": "21:08:02",
      "date": "2026-05-02",
      "traded": false,
      "tx": null
    },
    {
      "token": "Make Aliens Great Again ",
      "symbol": "MAGA",
      "address": "Hon2rHAiqkcDtUzL5gA2vjXPr7T1MPCK2UT2AHKCpump",
      "label": "BUY",
      "score": 50,
      "tech_score": 25,
      "narr_bonus": 25,
      "narrative": "\ud83e\udd16 AI Agent",
      "all_narratives": [
        "\ud83e\udd16 AI Agent",
        "\ud83c\udfdb\ufe0f PolitiFi"
      ],
      "price": 0.01742,
      "change_1h": 10.34,
      "liquidity": 445393.44,
      "volume_1h": 66901.66,
      "mcap": 17048952.0,
      "dex_url": "https://dexscreener.com/solana/hvimk99ygssdnwz9esqumdthrfz4dade7j6phmfms6at",
      "time": "21:08:02",
      "date": "2026-05-02",
      "traded": false,
      "tx": null
    },
    {
      "token": "Manfred",
      "symbol": "Manfred",
      "address": "2xbBHYkn6v5PGi19EHp9DiDDTjTB1QHKmwgxdQKx4xff",
      "label": "WATCH",
      "score": 37,
      "tech_score": 37,
      "narr_bonus": 0,
      "narrative": null,
      "all_narratives": [],
      "price": 3.949e-05,
      "change_1h": 40.59,
      "liquidity": 15509.53,
      "volume_1h": 6060.55,
      "mcap": 39492.0,
      "dex_url": "https://dexscreener.com/solana/dnezr75pnkgq7wdpywgctvu5yw9aohxa2bdkzsldfshg",
      "time": "21:08:02",
      "date": "2026-05-02",
      "traded": false,
      "tx": null
    },
    {
      "token": "LMEOW",
      "symbol": "LMEOW",
      "address": "3T3ePWvriBnF82Qp8PA8xD9cacVoqatzfuvFxMfLpump",
      "label": "BUY",
      "score": 63,
      "tech_score": 63,
      "narr_bonus": 0,
      "narrative": null,
      "all_narratives": [],
      "price": 0.000182,
      "change_1h": 393.0,
      "liquidity": 34604.14,
      "volume_1h": 356081.44,
      "mcap": 182088.0,
      "dex_url": "https://dexscreener.com/solana/b7wa7vqp28gx84atehvrne5giwnxrg6egdmx5dsqncuk",
      "time": "20:26:10",
      "date": "2026-05-02",
      "traded": false,
      "tx": null
    },
    {
      "token": "Go Getter",
      "symbol": "GETTER",
      "address": "uEBgmzYWX8RnJVPkkg7eoEtPSUQoxMPWBjyGqCipump",
      "label": "WATCH",
      "score": 40,
      "tech_score": 40,
      "narr_bonus": 0,
      "narrative": null,
      "all_narratives": [],
      "price": 4.557e-05,
      "change_1h": 34.51,
      "liquidity": 16622.18,
      "volume_1h": 109978.64,
      "mcap": 45569.0,
      "dex_url": "https://dexscreener.com/solana/6swpaw7xtnwirihzkjkd79w3c51cwiww6qfcrpsi1r7h",
      "time": "20:26:10",
      "date": "2026-05-02",
      "traded": false,
      "tx": null
    },
    {
      "token": "FUCK CANCER",
      "symbol": "FUCK",
      "address": "2GLBSneWiyf4LuaLgoqmzoGSzzQDJzR6evvZbhvvpump",
      "label": "WATCH",
      "score": 4,
      "tech_score": 4,
      "narr_bonus": 0,
      "narrative": null,
      "all_narratives": [],
      "price": 2.19e-06,
      "change_1h": 0.73,
      "liquidity": 3603.46,
      "volume_1h": 110.73,
      "mcap": 2190.0,
      "dex_url": "https://dexscreener.com/solana/adv5jpq1jctzptbeui19ciff5qeg2dhwfc4tgpd4gpvw",
      "time": "20:26:11",
      "date": "2026-05-02",
      "traded": false,
      "tx": null
    },
    {
      "token": "AMC",
      "symbol": "AMC",
      "address": "B85ta9Qp7EgoVXaMka9BQYrFogSmC3PRjsxNM6HaHF41",
      "label": "WATCH",
      "score": 26,
      "tech_score": 26,
      "narr_bonus": 0,
      "narrative": null,
      "all_narratives": [],
      "price": 6.619e-05,
      "change_1h": 6.05,
      "liquidity": 23960.45,
      "volume_1h": 3337.06,
      "mcap": 65067.0,
      "dex_url": "https://dexscreener.com/solana/8aeyhypxuey1jfasnnue1p1sgkhavnvbwbywplk8o6qz",
      "time": "20:26:12",
      "date": "2026-05-02",
      "traded": false,
      "tx": null
    },
    {
      "token": "Star Wars",
      "symbol": "May4th",
      "address": "7wC7z6FbueVpDhb724xg7VHvsLwMPuQgwvHUfMbq5Z89",
      "label": "WATCH",
      "score": 35,
      "tech_score": 35,
      "narr_bonus": 0,
      "narrative": null,
      "all_narratives": [],
      "price": 4.512e-05,
      "change_1h": 30.31,
      "liquidity": 16413.43,
      "volume_1h": 37542.19,
      "mcap": 44898.0,
      "dex_url": "https://dexscreener.com/solana/ahtjcjmi4rywkeo4ddfp18ym3wbcdym85uahxag9rdvu",
      "time": "20:26:12",
      "date": "2026-05-02",
      "traded": false,
      "tx": null
    },
    {
      "token": "LMEOW",
      "symbol": "LMEOW",
      "address": "3T3ePWvriBnF82Qp8PA8xD9cacVoqatzfuvFxMfLpump",
      "label": "BUY",
      "score": 56,
      "tech_score": 56,
      "narr_bonus": 0,
      "narrative": null,
      "all_narratives": [],
      "price": 8.575e-05,
      "change_1h": 147.0,
      "liquidity": 23350.98,
      "volume_1h": 346756.72,
      "mcap": 85758.0,
      "dex_url": "https://dexscreener.com/solana/b7wa7vqp28gx84atehvrne5giwnxrg6egdmx5dsqncuk",
      "time": "19:45:30",
      "date": "2026-05-02",
      "traded": false,
      "tx": null
    },
    {
      "token": "MS Paint Trump",
      "symbol": "MSTRUMP",
      "address": "GnqRKyQfcna6XbkoJMKkvUZUBQdtMb8oy5rH2ocpump",
      "label": "BUY",
      "score": 67,
      "tech_score": 42,
      "narr_bonus": 25,
      "narrative": "\ud83e\udd16 AI Agent",
      "all_narratives": [
        "\ud83e\udd16 AI Agent",
        "\ud83c\udfdb\ufe0f PolitiFi"
      ],
      "price": 0.0002003,
      "change_1h": 7.54,
      "liquidity": 35946.94,
      "volume_1h": 189074.97,
      "mcap": 200301.0,
      "dex_url": "https://dexscreener.com/solana/eakbwosvrxunpvbdszbeymxdbfxuxajq6snxqp2ezht1",
      "time": "19:45:31",
      "date": "2026-05-02",
      "traded": false,
      "tx": null
    },
    {
      "token": "MOJO",
      "symbol": "MOJO",
      "address": "sGzragYKDrmRgCGvJUn9WKwrmnUZwfmkNQLTSPfdMNq",
      "label": "WATCH",
      "score": 26,
      "tech_score": 26,
      "narr_bonus": 0,
      "narrative": null,
      "all_narratives": [],
      "price": 0.0004001,
      "change_1h": 15.17,
      "liquidity": 53363.44,
      "volume_1h": 4201.96,
      "mcap": 380105.0,
      "dex_url": "https://dexscreener.com/solana/b2kottpdfxoh3ygj4flq4yg9bo6jq9h3olgghes6hxoh",
      "time": "19:45:31",
      "date": "2026-05-02",
      "traded": false,
      "tx": null
    },
    {
      "token": "FLIP",
      "symbol": "FLIP",
      "address": "GdbJgfLXG5pBEibnrpSvfmXfbNKvyZkLQoTiQLoJpump",
      "label": "WATCH",
      "score": 40,
      "tech_score": 40,
      "narr_bonus": 0,
      "narrative": null,
      "all_narratives": [],
      "price": 0.0001562,
      "change_1h": 27.13,
      "liquidity": 31345.41,
      "volume_1h": 5415.59,
      "mcap": 156214.0,
      "dex_url": "https://dexscreener.com/solana/hnmivhgfjmgs6pm6e213m3p7vktbarmftezzsmgnx7db",
      "time": "19:45:32",
      "date": "2026-05-02",
      "traded": false,
      "tx": null
    },
    {
      "token": "This is Fine",
      "symbol": "FINE",
      "address": "3hHZ3QFWKVgUdi64uHJumK9T7hDR2Tr6WZBjUfP5pump",
      "label": "BUY",
      "score": 63,
      "tech_score": 63,
      "narr_bonus": 0,
      "narrative": null,
      "all_narratives": [],
      "price": 0.0002891,
      "change_1h": 272.0,
      "liquidity": 42401.56,
      "volume_1h": 264723.38,
      "mcap": 289161.0,
      "dex_url": "https://dexscreener.com/solana/cxn26rg96sff33bw8p6tya8qhvvepqmmy9b59dswbbfj",
      "time": "18:51:51",
      "date": "2026-05-02",
      "traded": false,
      "tx": null
    },
    {
      "token": "MS Paint Trump",
      "symbol": "MSTRUMP",
      "address": "GnqRKyQfcna6XbkoJMKkvUZUBQdtMb8oy5rH2ocpump",
      "label": "STRONG BUY",
      "score": 88,
      "tech_score": 63,
      "narr_bonus": 25,
      "narrative": "\ud83e\udd16 AI Agent",
      "all_narratives": [
        "\ud83e\udd16 AI Agent",
        "\ud83c\udfdb\ufe0f PolitiFi"
      ],
      "price": 0.0001993,
      "change_1h": 69.88,
      "liquidity": 35521.86,
      "volume_1h": 323307.05,
      "mcap": 199397.0,
      "dex_url": "https://dexscreener.com/solana/eakbwosvrxunpvbdszbeymxdbfxuxajq6snxqp2ezht1",
      "time": "18:51:52",
      "date": "2026-05-02",
      "traded": false,
      "tx": null
    },
    {
      "token": "dogwifouthat",
      "symbol": "wifout",
      "address": "CFWsZSFdtXV92KweDu4Mf5GEVVKK6zZPp21VJVjApump",
      "label": "STRONG BUY",
      "score": 83,
      "tech_score": 63,
      "narr_bonus": 20,
      "narrative": "\ud83d\udc3e Animal",
      "all_narratives": [
        "\ud83d\udc3e Animal"
      ],
      "price": 0.0001323,
      "change_1h": 283.0,
      "liquidity": 29144.79,
      "volume_1h": 444132.38,
      "mcap": 132391.0,
      "dex_url": "https://dexscreener.com/solana/7fmagjrzlpubfcofu5kxf76ibftnwkva43pcxvdumnpk",
      "time": "18:51:53",
      "date": "2026-05-02",
      "traded": false,
      "tx": null
    },
    {
      "token": "WINNING",
      "symbol": "WINNING",
      "address": "W1NqGUNfaxJpiKeeu9p8yxZNomPaC1ugLHeZ5ZvKC4m",
      "label": "WATCH",
      "score": 25,
      "tech_score": 25,
      "narr_bonus": 0,
      "narrative": null,
      "all_narratives": [],
      "price": 0.0001352,
      "change_1h": 1.08,
      "liquidity": 28463.79,
      "volume_1h": 32131.6,
      "mcap": 135238.0,
      "dex_url": "https://dexscreener.com/solana/93ktyxtigdz2dmygz7ug7tn9o3fxef7lz6jymeghpwpn",
      "time": "18:51:55",
      "date": "2026-05-02",
      "traded": false,
      "tx": null
    },
    {
      "token": "your onchain pet",
      "symbol": "memegotchi",
      "address": "BaCSr6omaLf113LfDDv9Wgb2dfGmJzKWvQhJB2QNpump",
      "label": "WATCH",
      "score": 33,
      "tech_score": 8,
      "narr_bonus": 25,
      "narrative": "\ud83e\udd16 AI Agent",
      "all_narratives": [
        "\ud83e\udd16 AI Agent",
        "\ud83d\ude02 Meme Culture"
      ],
      "price": 3.463e-06,
      "change_1h": 8.39,
      "liquidity": 4568.77,
      "volume_1h": 2469.21,
      "mcap": 3463.0,
      "dex_url": "https://dexscreener.com/solana/4jas4ambor3tzpp5ywg7wtxhawa2vzafc91s1d3xp7yn",
      "time": "18:51:55",
      "date": "2026-05-02",
      "traded": false,
      "tx": null
    },
    {
      "token": "Vincent For President",
      "symbol": "VINCENT",
      "address": "9xR3y1b3UPsSqnUVMWUhM5veq2grU6Cj8tjCvhPbpump",
      "label": "BUY",
      "score": 57,
      "tech_score": 35,
      "narr_bonus": 22,
      "narrative": "\ud83c\udfdb\ufe0f PolitiFi",
      "all_narratives": [
        "\ud83c\udfdb\ufe0f PolitiFi"
      ],
      "price": 3.233e-05,
      "change_1h": 95.77,
      "liquidity": 14382.94,
      "volume_1h": 18375.65,
      "mcap": 32325.0,
      "dex_url": "https://dexscreener.com/solana/edherp14mdmjwylhytzkq1swvkefszkvj4elax3vmprx",
      "time": "18:51:56",
      "date": "2026-05-02",
      "traded": false,
      "tx": null
    },
    {
      "token": "Spirit Airlines",
      "symbol": "Spirit",
      "address": "HXzqEEUjQ6JevbrJiMBAwoiCVikZb93XHmYtde4iCA3G",
      "label": "BUY",
      "score": 60,
      "tech_score": 35,
      "narr_bonus": 25,
      "narrative": "\ud83e\udd16 AI Agent",
      "all_narratives": [
        "\ud83e\udd16 AI Agent"
      ],
      "price": 0.0002075,
      "change_1h": 32.68,
      "liquidity": 38183.8,
      "volume_1h": 59996.3,
      "mcap": 207553.0,
      "dex_url": "https://dexscreener.com/solana/2skzvnpfueyff79hkcew2va4wasnv3a2f3zrstwhkvn2",
      "time": "18:51:56",
      "date": "2026-05-02",
      "traded": false,
      "tx": null
    },
    {
      "token": "Anon Alien",
      "symbol": "AALIEN",
      "address": "ARea51UmRfn22Ds7KwFZirSMEEn1gtBdrhW4zLeveeV1",
      "label": "WATCH",
      "score": 33,
      "tech_score": 33,
      "narr_bonus": 0,
      "narrative": null,
      "all_narratives": [],
      "price": 0.000377,
      "change_1h": 4.15,
      "liquidity": 50564.33,
      "volume_1h": 22725.89,
      "mcap": 377097.0,
      "dex_url": "https://dexscreener.com/solana/4prwf2thuksaqwfmmz53mtatqtc18gzbrddw9empwsnp",
      "time": "18:51:56",
      "date": "2026-05-02",
      "traded": false,
      "tx": null
    },
    {
      "token": "WINNING",
      "symbol": "WINNING",
      "address": "W1NqGUNfaxJpiKeeu9p8yxZNomPaC1ugLHeZ5ZvKC4m",
      "label": "WATCH",
      "score": 43,
      "tech_score": 43,
      "narr_bonus": 0,
      "narrative": null,
      "all_narratives": [],
      "price": 0.0001395,
      "change_1h": 91.28,
      "liquidity": 28816.17,
      "volume_1h": 34137.42,
      "mcap": 139554.0,
      "dex_url": "https://dexscreener.com/solana/93ktyxtigdz2dmygz7ug7tn9o3fxef7lz6jymeghpwpn",
      "time": "17:54:05",
      "date": "2026-05-02",
      "traded": false,
      "tx": null
    },
    {
      "token": "Luigi Got Big Titties ",
      "symbol": "LGBT",
      "address": "CLJJs8pSkSkgHvzeZRoS1Jkge7SxPhd9LrJmArvSpump",
      "label": "WATCH",
      "score": 40,
      "tech_score": 40,
      "narr_bonus": 0,
      "narrative": null,
      "all_narratives": [],
      "price": 4.453e-05,
      "change_1h": 28.58,
      "liquidity": 16298.68,
      "volume_1h": 56194.3,
      "mcap": 44538.0,
      "dex_url": "https://dexscreener.com/solana/2htxztychqjsxopag1dqspxmukcvug5rssrflvbkvsuq",
      "time": "17:54:06",
      "date": "2026-05-02",
      "traded": false,
      "tx": null
    },
    {
      "token": "Pied Piper",
      "symbol": "Piper",
      "address": "83VTqzxszRFPSzJHvTeNRydcuUmmhEjj9FH4F7TZpump",
      "label": "WATCH",
      "score": 17,
      "tech_score": 17,
      "narr_bonus": 0,
      "narrative": null,
      "all_narratives": [],
      "price": 1.098e-05,
      "change_1h": 3.84,
      "liquidity": 8067.96,
      "volume_1h": 12775.49,
      "mcap": 10982.0,
      "dex_url": "https://dexscreener.com/solana/4z2dpdqa6fw8drt1dwnxxbrsqkbcfkvzxnj7f37uxi7b",
      "time": "17:54:06",
      "date": "2026-05-02",
      "traded": false,
      "tx": null
    },
    {
      "token": "AINL",
      "symbol": "AINL",
      "address": "56hrCR3n7danhHNjWaU4VeUHpE1eRE9VRBWpHRPKpump",
      "label": "BUY",
      "score": 52,
      "tech_score": 27,
      "narr_bonus": 25,
      "narrative": "\ud83e\udd16 AI Agent",
      "all_narratives": [
        "\ud83e\udd16 AI Agent"
      ],
      "price": 0.0005233,
      "change_1h": 2.32,
      "liquidity": 58827.28,
      "volume_1h": 3185.24,
      "mcap": 523258.0,
      "dex_url": "https://dexscreener.com/solana/6dnmwxhcrbuixe5m3clqkicgo1xvuwkfjh3s9utvh3mx",
      "time": "17:54:07",
      "date": "2026-05-02",
      "traded": false,
      "tx": null
    },
    {
      "token": "Little Flash",
      "symbol": "Flash",
      "address": "pACMKYiCAygMH4UXfQbs86g2Yv5FidV8QytvVEhpump",
      "label": "WATCH",
      "score": 38,
      "tech_score": 38,
      "narr_bonus": 0,
      "narrative": null,
      "all_narratives": [],
      "price": 9.432e-05,
      "change_1h": 15.54,
      "liquidity": 27868.2,
      "volume_1h": 994.74,
      "mcap": 94214.0,
      "dex_url": "https://dexscreener.com/solana/5egthklgbfougwkau2cy7w5osdgdye9dzjb2w18urjwx",
      "time": "17:54:07",
      "date": "2026-05-02",
      "traded": false,
      "tx": null
    },
    {
      "token": "Save Lucy",
      "symbol": "LUCY",
      "address": "GNL7MQSzzksbfuquHTJuiDPVXvXpfxBfHfu1mQGhpump",
      "label": "BUY",
      "score": 51,
      "tech_score": 51,
      "narr_bonus": 0,
      "narrative": null,
      "all_narratives": [],
      "price": 4.47e-05,
      "change_1h": 150.0,
      "liquidity": 16325.2,
      "volume_1h": 17287.74,
      "mcap": 44709.0,
      "dex_url": "https://dexscreener.com/solana/d8qs5frs59frlzmarkvnuxqctnqlkmqytck4dbmuhrcv",
      "time": "17:54:08",
      "date": "2026-05-02",
      "traded": false,
      "tx": null
    },
    {
      "token": "Vincent For President",
      "symbol": "VINCENT",
      "address": "9xR3y1b3UPsSqnUVMWUhM5veq2grU6Cj8tjCvhPbpump",
      "label": "STRONG BUY",
      "score": 70,
      "tech_score": 48,
      "narr_bonus": 22,
      "narrative": "\ud83c\udfdb\ufe0f PolitiFi",
      "all_narratives": [
        "\ud83c\udfdb\ufe0f PolitiFi"
      ],
      "price": 5.994e-05,
      "change_1h": 72.96,
      "liquidity": 19308.2,
      "volume_1h": 227796.77,
      "mcap": 59946.0,
      "dex_url": "https://dexscreener.com/solana/edherp14mdmjwylhytzkq1swvkefszkvj4elax3vmprx",
      "time": "16:59:51",
      "date": "2026-05-02",
      "traded": false,
      "tx": null
    },
    {
      "token": "Do Only Good Everyday",
      "symbol": "DOGE",
      "address": "E4tPSmY1EtFKfeDaqBfAgbauBpFtvPwS4iQMDfpSpump",
      "label": "STRONG BUY",
      "score": 73,
      "tech_score": 51,
      "narr_bonus": 22,
      "narrative": "\ud83c\udfdb\ufe0f PolitiFi",
      "all_narratives": [
        "\ud83c\udfdb\ufe0f PolitiFi",
        "\ud83d\udc3e Animal"
      ],
      "price": 5.152e-05,
      "change_1h": 133.0,
      "liquidity": 17685.5,
      "volume_1h": 84512.72,
      "mcap": 51520.0,
      "dex_url": "https://dexscreener.com/solana/8b6cnzjnjlf8xhpvlnoriaudbyuzepn1wc2wfetn534r",
      "time": "16:59:53",
      "date": "2026-05-02",
      "traded": false,
      "tx": null
    },
    {
      "token": "Save Lucy",
      "symbol": "LUCY",
      "address": "GNL7MQSzzksbfuquHTJuiDPVXvXpfxBfHfu1mQGhpump",
      "label": "WATCH",
      "score": 21,
      "tech_score": 21,
      "narr_bonus": 0,
      "narrative": null,
      "all_narratives": [],
      "price": 1.99e-05,
      "change_1h": 12.07,
      "liquidity": 10897.76,
      "volume_1h": 10806.61,
      "mcap": 19907.0,
      "dex_url": "https://dexscreener.com/solana/d8qs5frs59frlzmarkvnuxqctnqlkmqytck4dbmuhrcv",
      "time": "16:59:54",
      "date": "2026-05-02",
      "traded": false,
      "tx": null
    },
    {
      "token": "RECON RACCOON",
      "symbol": "RCON",
      "address": "7nZuYZYZnof9gF3zr9QhdnxpQ1mTM8LN3VaJuhrGbonk",
      "label": "WATCH",
      "score": 21,
      "tech_score": 21,
      "narr_bonus": 0,
      "narrative": null,
      "all_narratives": [],
      "price": 0.003045,
      "change_1h": 1.25,
      "liquidity": 140744.25,
      "volume_1h": 46848.33,
      "mcap": 3045676.0,
      "dex_url": "https://dexscreener.com/solana/gcxnezvgsn3sj753ak6mcca43gsjlmnvfhyqva2bsf4k",
      "time": "16:59:54",
      "date": "2026-05-02",
      "traded": false,
      "tx": null
    },
    {
      "token": "blind goblin",
      "symbol": "BLINDGOBLIN",
      "address": "J34kJALFnK2ysjHC8aprkzn3uEf2x1BRC3WMWQswpump",
      "label": "BUY",
      "score": 63,
      "tech_score": 63,
      "narr_bonus": 0,
      "narrative": null,
      "all_narratives": [],
      "price": 0.0001911,
      "change_1h": 77.9,
      "liquidity": 35225.8,
      "volume_1h": 244481.11,
      "mcap": 191111.0,
      "dex_url": "https://dexscreener.com/solana/rmteebpb4pduopqcvyqiqdiszz73rzyzpmx2d4ntqxe",
      "time": "15:59:09",
      "date": "2026-05-02",
      "traded": false,
      "tx": null
    },
    {
      "token": "WINNING",
      "symbol": "WINNING",
      "address": "5U7yW5CRQaj13whEjkq4bPF6gagTKAGtkT84ubfEpump",
      "label": "STRONG BUY",
      "score": 76,
      "tech_score": 76,
      "narr_bonus": 0,
      "narrative": null,
      "all_narratives": [],
      "price": 0.0002985,
      "change_1h": 192.0,
      "liquidity": 43959.36,
      "volume_1h": 563833.64,
      "mcap": 298554.0,
      "dex_url": "https://dexscreener.com/solana/8xn2px6prbpjsgmwxqt4efkaelrpjqohrjd1p7dgrjfn",
      "time": "15:59:09",
      "date": "2026-05-02",
      "traded": false,
      "tx": null
    },
    {
      "token": "Goblin Brainlet",
      "symbol": "GOBRAIN",
      "address": "EzwfY3hkGL4JCfnXkyMQJYyr3o9hNSvG1ugcXrpLpump",
      "label": "WATCH",
      "score": 33,
      "tech_score": 8,
      "narr_bonus": 25,
      "narrative": "\ud83e\udd16 AI Agent",
      "all_narratives": [
        "\ud83e\udd16 AI Agent"
      ],
      "price": 2.247e-06,
      "change_1h": 14.12,
      "liquidity": 3787.38,
      "volume_1h": 347.48,
      "mcap": 2247.0,
      "dex_url": "https://dexscreener.com/solana/bgucqui89tskrmtslmc2t8hdr1ogbwk5axksugtbvkxc",
      "time": "15:59:10",
      "date": "2026-05-02",
      "traded": false,
      "tx": null
    },
    {
      "token": "Three Points",
      "symbol": "Points",
      "address": "8vvjTTH1SDqYXhZJ6axBoc5NT8LBNfaNa9tmRqtXpump",
      "label": "WATCH",
      "score": 32,
      "tech_score": 32,
      "narr_bonus": 0,
      "narrative": null,
      "all_narratives": [],
      "price": 3.958e-06,
      "change_1h": 95.14,
      "liquidity": 5085.46,
      "volume_1h": 5101.74,
      "mcap": 3958.0,
      "dex_url": "https://dexscreener.com/solana/fve5b6um5jy28nevuvkkenophgqfjpyls1szv55rvfan",
      "time": "15:59:11",
      "date": "2026-05-02",
      "traded": false,
      "tx": null
    },
    {
      "token": "VigilFi",
      "symbol": "VIGIL",
      "address": "F3iV4HCdr4rBCHmLZPEEFiLxBwznSVwPYx2AoQy5pump",
      "label": "WATCH",
      "score": 43,
      "tech_score": 43,
      "narr_bonus": 0,
      "narrative": null,
      "all_narratives": [],
      "price": 0.00012,
      "change_1h": 67.01,
      "liquidity": 26997.32,
      "volume_1h": 34113.85,
      "mcap": 119670.0,
      "dex_url": "https://dexscreener.com/solana/5nl3rqqg837wbhggq8f12fqbcpkmcf4mzgzsrs2ukhmn",
      "time": "15:59:11",
      "date": "2026-05-02",
      "traded": false,
      "tx": null
    },
    {
      "token": "Shoebill",
      "symbol": "Shoebill",
      "address": "HdyNAGhuDjtuyiDmCnozH67gEV3RiQHcdBXcCxF14JZc",
      "label": "WATCH",
      "score": 34,
      "tech_score": 34,
      "narr_bonus": 0,
      "narrative": null,
      "all_narratives": [],
      "price": 2.25e-06,
      "change_1h": 32.24,
      "liquidity": 3688.74,
      "volume_1h": 571.23,
      "mcap": 2249.0,
      "dex_url": "https://dexscreener.com/solana/3rbsthmmmgubyojyotssby6exdumfcwvrypj79zmc4xc",
      "time": "15:59:11",
      "date": "2026-05-02",
      "traded": false,
      "tx": null
    },
    {
      "token": "2026 World Cup Mascots",
      "symbol": "MASCOTS",
      "address": "8GxLxKA8tf3h8JUkXFfP4dNyn6D2vvwyGif5wanRpump",
      "label": "WATCH",
      "score": 18,
      "tech_score": 18,
      "narr_bonus": 0,
      "narrative": null,
      "all_narratives": [],
      "price": 0.0001467,
      "change_1h": 10.15,
      "liquidity": 36345.17,
      "volume_1h": 1887.86,
      "mcap": 146768.0,
      "dex_url": "https://dexscreener.com/solana/d2g8aauqbzlpx7mxp6yg8v3psau6hvc2drlqjuaqxzyp",
      "time": "15:59:12",
      "date": "2026-05-02",
      "traded": false,
      "tx": null
    },
    {
      "token": "Purple Bitcoin",
      "symbol": "PBTC",
      "address": "HfMbPyDdZH6QMaDDUokjYCkHxzjoGBMpgaUvpLWGbF5p",
      "label": "WATCH",
      "score": 31,
      "tech_score": 21,
      "narr_bonus": 10,
      "narrative": "\ud83d\udcb0 DeFi",
      "all_narratives": [
        "\ud83d\udcb0 DeFi"
      ],
      "price": 0.1875,
      "change_1h": 2.89,
      "liquidity": 235962.94,
      "volume_1h": 22261.18,
      "mcap": 3622289.0,
      "dex_url": "https://dexscreener.com/solana/ath32pblrupjq8ynuhqwajbgbbgprbrw2gzw5jdzxirr",
      "time": "15:59:12",
      "date": "2026-05-02",
      "traded": false,
      "tx": null
    },
    {
      "token": "WINNING",
      "symbol": "WINNING",
      "address": "JAxMg5ErnK6ji37TnUh89yA2mouDkFVpiKGaEi1mpump",
      "label": "STRONG BUY",
      "score": 78,
      "tech_score": 78,
      "narr_bonus": 0,
      "narrative": null,
      "all_narratives": [],
      "price": 0.0003464,
      "change_1h": 904.0,
      "liquidity": 48176.36,
      "volume_1h": 1114646.6,
      "mcap": 346424.0,
      "dex_url": "https://dexscreener.com/solana/14oc5fwdntu4r2hukldnmux12jneh183fpn9venljjoa",
      "time": "15:07:17",
      "date": "2026-05-02",
      "traded": false,
      "tx": null
    }
  ],
  "trades": [],
  "stats": {
    "scans": 772,
    "signals": 4300,
    "trades": 0
  },
  "wallet": {
    "address": "",
    "balance": 0.2
  },
  "last_scan": "2026-05-02 21:57:19 UTC"
}